{
  "service_code": "275c",
  "line_name": "275",
  "origin": "Halkirk",
  "destination": "Dounreay",
  "stops": [
    [
      58.51451,
      -3.48975
    ],
    [
      58.51401,
      -3.49428
    ],
    [
      58.51565,
      -3.49557
    ],
    [
      58.51937,
      -3.49621
    ],
    [
      58.53366,
      -3.50182
    ],
    [
      58.54966,
      -3.51562
    ],
    [
      58.5549,
      -3.52529
    ],
    [
      58.56269,
      -3.53634
    ],
    [
      58.57163,
      -3.54577
    ],
    [
      58.57602,
      -3.54759
    ],
    [
      58.58354,
      -3.53771
    ],
    [
      58.5851,
      -3.53641
    ],
    [
      58.58567,
      -3.53594
    ],
    [
      58.591604,
      -3.531326
    ],
    [
      58.5939,
      -3.53371
    ],
    [
      58.596519,
      -3.533468
    ],
    [
      58.59819,
      -3.54078
    ],
    [
      58.597962,
      -3.55468
    ],
    [
      58.60098,
      -3.62775
    ],
    [
      58.597981,
      -3.642217
    ],
    [
      58.59657,
      -3.6513
    ],
    [
      58.594728,
      -3.663781
    ],
    [
      58.59681,
      -3.68089
    ],
    [
      58.585259,
      -3.711722
    ],
    [
      58.57888,
      -3.72782
    ],
    [
      58.57956,
      -3.73533
    ]
  ]
}