{
  "service_code": "290",
  "line_name": "291",
  "origin": "Aberdeen Union Square",
  "destination": "Methlick",
  "stops": [
    [
      57.144379,
      -2.09596
    ],
    [
      57.147178,
      -2.096426
    ],
    [
      57.150604,
      -2.093966
    ],
    [
      57.152697,
      -2.094466
    ],
    [
      57.155516,
      -2.095131
    ],
    [
      57.157608,
      -2.095631
    ],
    [
      57.159916,
      -2.096192
    ],
    [
      57.161775,
      -2.096647
    ],
    [
      57.163642,
      -2.097102
    ],
    [
      57.165124,
      -2.09745
    ],
    [
      57.167468,
      -2.096669
    ],
    [
      57.170604,
      -2.095059
    ],
    [
      57.17261,
      -2.093359
    ],
    [
      57.174087,
      -2.091719
    ],
    [
      57.176704,
      -2.09022
    ],
    [
      57.178041,
      -2.090322
    ],
    [
      57.180411,
      -2.090849
    ],
    [
      57.185293,
      -2.090176
    ],
    [
      57.188369,
      -2.09173
    ],
    [
      57.190079,
      -2.092802
    ],
    [
      57.192124,
      -2.092855
    ],
    [
      57.194489,
      -2.093962
    ],
    [
      57.199035,
      -2.092667
    ],
    [
      57.20118,
      -2.09247
    ],
    [
      57.202927,
      -2.092862
    ],
    [
      57.214417,
      -2.096484
    ],
    [
      57.231092,
      -2.101817
    ],
    [
      57.254389,
      -2.129329
    ],
    [
      57.290884,
      -2.147449
    ],
    [
      57.310351,
      -2.152241
    ],
    [
      57.310009,
      -2.165511
    ],
    [
      57.332064,
      -2.171427
    ],
    [
      57.335837,
      -2.177187
    ],
    [
      57.337192,
      -2.180436
    ],
    [
      57.33958,
      -2.1825
    ],
    [
      57.341077,
      -2.183934
    ],
    [
      57.351988,
      -2.197807
    ],
    [
      57.370367,
      -2.216605
    ],
    [
      57.371128,
      -2.221334
    ],
    [
      57.370356,
      -2.224345
    ],
    [
      57.369579,
      -2.228189
    ],
    [
      57.392522,
      -2.25477
    ],
    [
      57.406418,
      -2.252767
    ],
    [
      57.426582,
      -2.240812
    ]
  ]
}