{
  "service_code": "32",
  "line_name": "32",
  "origin": "Elgin (Bus Station)",
  "destination": "Burghead",
  "stops": [
    [
      57.649439,
      -3.316186
    ],
    [
      57.64987,
      -3.32185
    ],
    [
      57.65109,
      -3.32177
    ],
    [
      57.65192,
      -3.31738
    ],
    [
      57.655635,
      -3.317498
    ],
    [
      57.65675,
      -3.319114
    ],
    [
      57.656691,
      -3.325269
    ],
    [
      57.65755,
      -3.33171
    ],
    [
      57.659263,
      -3.340001
    ],
    [
      57.66308,
      -3.36023
    ],
    [
      57.67665,
      -3.37865
    ],
    [
      57.6995,
      -3.39514
    ],
    [
      57.70316,
      -3.4106
    ],
    [
      57.706108,
      -3.426775
    ],
    [
      57.705553,
      -3.430496
    ],
    [
      57.70507,
      -3.43395
    ],
    [
      57.70426,
      -3.43971
    ],
    [
      57.702369,
      -3.454684
    ],
    [
      57.70148,
      -3.46065
    ],
    [
      57.70187,
      -3.47487
    ],
    [
      57.701572,
      -3.477844
    ],
    [
      57.701228,
      -3.47987
    ],
    [
      57.70035,
      -3.48309
    ],
    [
      57.700525,
      -3.486615
    ],
    [
      57.701572,
      -3.49097
    ],
    [
      57.702205,
      -3.493604
    ],
    [
      57.7015,
      -3.49536
    ]
  ]
}