{
  "service_code": "F037",
  "line_name": "37",
  "origin": "Kirkcaldy Bus Station",
  "destination": "Glenrothes Bus Station",
  "stops": [
    [
      56.10984,
      -3.161091
    ],
    [
      56.11342,
      -3.16527
    ],
    [
      56.11737,
      -3.16862
    ],
    [
      56.11944,
      -3.16892
    ],
    [
      56.12099,
      -3.16975
    ],
    [
      56.12202,
      -3.16986
    ],
    [
      56.12336,
      -3.16825
    ],
    [
      56.12323,
      -3.16532
    ],
    [
      56.12304,
      -3.16339
    ],
    [
      56.12361,
      -3.15798
    ],
    [
      56.126995,
      -3.15546
    ],
    [
      56.12707,
      -3.15059
    ],
    [
      56.12508,
      -3.14702
    ],
    [
      56.12452,
      -3.14349
    ],
    [
      56.12519,
      -3.14094
    ],
    [
      56.129,
      -3.13712
    ],
    [
      56.13044,
      -3.13606
    ],
    [
      56.13283,
      -3.13247
    ],
    [
      56.13538,
      -3.13195
    ],
    [
      56.13931,
      -3.13473
    ],
    [
      56.14648,
      -3.1404
    ],
    [
      56.15297,
      -3.14086
    ],
    [
      56.16029,
      -3.14342
    ],
    [
      56.16112,
      -3.14366
    ],
    [
      56.16373,
      -3.14499
    ],
    [
      56.16629,
      -3.1462
    ],
    [
      56.16883,
      -3.14611
    ],
    [
      56.17299,
      -3.14555
    ],
    [
      56.17814,
      -3.13955
    ],
    [
      56.18171,
      -3.140169
    ],
    [
      56.1839,
      -3.13983
    ],
    [
      56.185405,
      -3.144303
    ],
    [
      56.18504,
      -3.14742
    ],
    [
      56.18964,
      -3.14969
    ],
    [
      56.19184,
      -3.15057
    ],
    [
      56.19356,
      -3.15102
    ],
    [
      56.19706,
      -3.16188
    ],
    [
      56.19523,
      -3.16959
    ]
  ]
}