{
  "service_code": "S063",
  "line_name": "63",
  "origin": "Blairgowrie",
  "destination": "Town Service",
  "stops": [
    [
      56.5913,
      -3.33684
    ],
    [
      56.59106,
      -3.34015
    ],
    [
      56.58944,
      -3.34245
    ],
    [
      56.58799,
      -3.34383
    ],
    [
      56.58645,
      -3.3447
    ],
    [
      56.58445,
      -3.34504
    ],
    [
      56.5831,
      -3.34524
    ],
    [
      56.58163,
      -3.34549
    ],
    [
      56.57971,
      -3.34582
    ],
    [
      56.57699,
      -3.34707
    ],
    [
      56.57458,
      -3.34717
    ],
    [
      56.56833,
      -3.34706
    ],
    [
      56.57443,
      -3.34716
    ],
    [
      56.57681,
      -3.34714
    ],
    [
      56.57957,
      -3.34584
    ],
    [
      56.58145,
      -3.34552
    ],
    [
      56.58289,
      -3.34527
    ],
    [
      56.5854,
      -3.34488
    ],
    [
      56.58602,
      -3.34647
    ],
    [
      56.58694,
      -3.34461
    ],
    [
      56.58871,
      -3.34314
    ],
    [
      56.59046,
      -3.34144
    ],
    [
      56.59199,
      -3.34005
    ],
    [
      56.5906,
      -3.33587
    ],
    [
      56.59124,
      -3.33691
    ],
    [
      56.5913,
      -3.33684
    ],
    [
      56.59352,
      -3.33171
    ],
    [
      56.59453,
      -3.32916
    ],
    [
      56.59567,
      -3.33097
    ],
    [
      56.59648,
      -3.3311
    ],
    [
      56.59665,
      -3.329
    ],
    [
      56.59798,
      -3.32702
    ],
    [
      56.59819,
      -3.32875
    ],
    [
      56.59797,
      -3.33159
    ],
    [
      56.59891,
      -3.33555
    ],
    [
      56.6011,
      -3.34025
    ],
    [
      56.5908,
      -3.33003
    ],
    [
      56.58831,
      -3.32718
    ],
    [
      56.58813,
      -3.31922
    ],
    [
      56.58918,
      -3.3199
    ],
    [
      56.59093,
      -3.33289
    ],
    [
      56.59229,
      -3.33431
    ],
    [
      56.5906,
      -3.33587
    ],
    [
      56.59124,
      -3.33691
    ],
    [
      56.5913,
      -3.33684
    ],
    [
      56.59106,
      -3.34015
    ],
    [
      56.58944,
      -3.34245
    ],
    [
      56.58799,
      -3.34383
    ],
    [
      56.58602,
      -3.34647
    ],
    [
      56.58494,
      -3.34276
    ],
    [
      56.58444,
      -3.33879
    ],
    [
      56.58276,
      -3.33771
    ],
    [
      56.58171,
      -3.34171
    ],
    [
      56.58244,
      -3.34368
    ],
    [
      56.58256,
      -3.34062
    ],
    [
      56.58374,
      -3.3394
    ],
    [
      56.58808,
      -3.34113
    ],
    [
      56.59106,
      -3.34015
    ],
    [
      56.59199,
      -3.34005
    ],
    [
      56.5906,
      -3.33587
    ],
    [
      56.59124,
      -3.33691
    ]
  ]
}