{
  "line": "365",
  "origin": "Charlotte Street, Stranraer",
  "destination": "Charlotte Street, Stranraer",
  "serviceCode": "365",
  "routeData": {
    "totalDistance": 18228.5,
    "totalTime": 2021.799999999,
    "coordinates": [
      {
        "lat": 54.904632,
        "lng": -5.026111
      },
      {
        "lat": 54.904641,
        "lng": -5.025874
      },
      {
        "lat": 54.90465,
        "lng": -5.025721
      },
      {
        "lat": 54.904666,
        "lng": -5.025612
      },
      {
        "lat": 54.904701,
        "lng": -5.025361
      },
      {
        "lat": 54.90477,
        "lng": -5.024912
      },
      {
        "lat": 54.904852,
        "lng": -5.024565
      },
      {
        "lat": 54.904936,
        "lng": -5.024236
      },
      {
        "lat": 54.904958,
        "lng": -5.024097
      },
      {
        "lat": 54.905,
        "lng": -5.024012
      },
      {
        "lat": 54.905173,
        "lng": -5.023749
      },
      {
        "lat": 54.905285,
        "lng": -5.023672
      },
      {
        "lat": 54.905362,
        "lng": -5.023592
      },
      {
        "lat": 54.905372,
        "lng": -5.0236
      },
      {
        "lat": 54.905389,
        "lng": -5.023786
      },
      {
        "lat": 54.9054,
        "lng": -5.023865
      },
      {
        "lat": 54.9054,
        "lng": -5.024173
      },
      {
        "lat": 54.905376,
        "lng": -5.024403
      },
      {
        "lat": 54.905373,
        "lng": -5.02447
      },
      {
        "lat": 54.905369,
        "lng": -5.024541
      },
      {
        "lat": 54.905365,
        "lng": -5.02464
      },
      {
        "lat": 54.90537,
        "lng": -5.024767
      },
      {
        "lat": 54.905413,
        "lng": -5.025413
      },
      {
        "lat": 54.905463,
        "lng": -5.026144
      },
      {
        "lat": 54.905483,
        "lng": -5.02645
      },
      {
        "lat": 54.905485,
        "lng": -5.02647
      },
      {
        "lat": 54.905492,
        "lng": -5.026526
      },
      {
        "lat": 54.905507,
        "lng": -5.026599
      },
      {
        "lat": 54.905528,
        "lng": -5.026665
      },
      {
        "lat": 54.905553,
        "lng": -5.026726
      },
      {
        "lat": 54.905694,
        "lng": -5.02702
      },
      {
        "lat": 54.905734,
        "lng": -5.027104
      },
      {
        "lat": 54.905752,
        "lng": -5.027154
      },
      {
        "lat": 54.905769,
        "lng": -5.027219
      },
      {
        "lat": 54.905773,
        "lng": -5.027247
      },
      {
        "lat": 54.90578,
        "lng": -5.027273
      },
      {
        "lat": 54.905809,
        "lng": -5.027515
      },
      {
        "lat": 54.905837,
        "lng": -5.027917
      },
      {
        "lat": 54.905833,
        "lng": -5.028637
      },
      {
        "lat": 54.905815,
        "lng": -5.029456
      },
      {
        "lat": 54.905788,
        "lng": -5.029927
      },
      {
        "lat": 54.905785,
        "lng": -5.030376
      },
      {
        "lat": 54.905784,
        "lng": -5.030761
      },
      {
        "lat": 54.905787,
        "lng": -5.030988
      },
      {
        "lat": 54.90579,
        "lng": -5.031166
      },
      {
        "lat": 54.905805,
        "lng": -5.031446
      },
      {
        "lat": 54.905824,
        "lng": -5.031618
      },
      {
        "lat": 54.905844,
        "lng": -5.031746
      },
      {
        "lat": 54.905889,
        "lng": -5.031981
      },
      {
        "lat": 54.905944,
        "lng": -5.032231
      },
      {
        "lat": 54.905978,
        "lng": -5.032359
      },
      {
        "lat": 54.905999,
        "lng": -5.032439
      },
      {
        "lat": 54.90618,
        "lng": -5.032998
      },
      {
        "lat": 54.906319,
        "lng": -5.033471
      },
      {
        "lat": 54.906409,
        "lng": -5.033755
      },
      {
        "lat": 54.906528,
        "lng": -5.034093
      },
      {
        "lat": 54.906612,
        "lng": -5.034314
      },
      {
        "lat": 54.906672,
        "lng": -5.034467
      },
      {
        "lat": 54.906759,
        "lng": -5.034671
      },
      {
        "lat": 54.906852,
        "lng": -5.034867
      },
      {
        "lat": 54.906926,
        "lng": -5.035009
      },
      {
        "lat": 54.907004,
        "lng": -5.035145
      },
      {
        "lat": 54.907085,
        "lng": -5.035276
      },
      {
        "lat": 54.907113,
        "lng": -5.035312
      },
      {
        "lat": 54.907192,
        "lng": -5.035412
      },
      {
        "lat": 54.907261,
        "lng": -5.035489
      },
      {
        "lat": 54.907281,
        "lng": -5.035509
      },
      {
        "lat": 54.90739,
        "lng": -5.035617
      },
      {
        "lat": 54.907509,
        "lng": -5.035723
      },
      {
        "lat": 54.90786,
        "lng": -5.036011
      },
      {
        "lat": 54.908863,
        "lng": -5.036763
      },
      {
        "lat": 54.909422,
        "lng": -5.037165
      },
      {
        "lat": 54.909537,
        "lng": -5.03725
      },
      {
        "lat": 54.909796,
        "lng": -5.037402
      },
      {
        "lat": 54.909899,
        "lng": -5.03751
      },
      {
        "lat": 54.910101,
        "lng": -5.037805
      },
      {
        "lat": 54.9105,
        "lng": -5.038447
      },
      {
        "lat": 54.910516,
        "lng": -5.038476
      },
      {
        "lat": 54.910617,
        "lng": -5.03866
      },
      {
        "lat": 54.910734,
        "lng": -5.038871
      },
      {
        "lat": 54.911064,
        "lng": -5.03965
      },
      {
        "lat": 54.911106,
        "lng": -5.039778
      },
      {
        "lat": 54.911142,
        "lng": -5.039889
      },
      {
        "lat": 54.911646,
        "lng": -5.042331
      },
      {
        "lat": 54.911654,
        "lng": -5.042373
      },
      {
        "lat": 54.911733,
        "lng": -5.042822
      },
      {
        "lat": 54.911834,
        "lng": -5.043396
      },
      {
        "lat": 54.911898,
        "lng": -5.043717
      },
      {
        "lat": 54.911911,
        "lng": -5.043773
      },
      {
        "lat": 54.911978,
        "lng": -5.044078
      },
      {
        "lat": 54.912081,
        "lng": -5.044487
      },
      {
        "lat": 54.912291,
        "lng": -5.045119
      },
      {
        "lat": 54.912477,
        "lng": -5.045676
      },
      {
        "lat": 54.912682,
        "lng": -5.046306
      },
      {
        "lat": 54.912828,
        "lng": -5.046755
      },
      {
        "lat": 54.913216,
        "lng": -5.047856
      },
      {
        "lat": 54.912977,
        "lng": -5.047998
      },
      {
        "lat": 54.912926,
        "lng": -5.047315
      },
      {
        "lat": 54.912628,
        "lng": -5.046436
      },
      {
        "lat": 54.91264,
        "lng": -5.04647
      },
      {
        "lat": 54.912926,
        "lng": -5.047315
      },
      {
        "lat": 54.912977,
        "lng": -5.047998
      },
      {
        "lat": 54.913216,
        "lng": -5.047856
      },
      {
        "lat": 54.913541,
        "lng": -5.048721
      },
      {
        "lat": 54.913645,
        "lng": -5.04864
      },
      {
        "lat": 54.913841,
        "lng": -5.048485
      },
      {
        "lat": 54.9141,
        "lng": -5.048282
      },
      {
        "lat": 54.914462,
        "lng": -5.048018
      },
      {
        "lat": 54.914582,
        "lng": -5.047954
      },
      {
        "lat": 54.914543,
        "lng": -5.047748
      },
      {
        "lat": 54.914419,
        "lng": -5.047319
      },
      {
        "lat": 54.913766,
        "lng": -5.045067
      },
      {
        "lat": 54.913724,
        "lng": -5.045009
      },
      {
        "lat": 54.913619,
        "lng": -5.04497
      },
      {
        "lat": 54.913532,
        "lng": -5.045021
      },
      {
        "lat": 54.913135,
        "lng": -5.045273
      },
      {
        "lat": 54.91262,
        "lng": -5.045586
      },
      {
        "lat": 54.912574,
        "lng": -5.045614
      },
      {
        "lat": 54.912477,
        "lng": -5.045676
      },
      {
        "lat": 54.912081,
        "lng": -5.044487
      },
      {
        "lat": 54.911978,
        "lng": -5.044078
      },
      {
        "lat": 54.911911,
        "lng": -5.043773
      },
      {
        "lat": 54.911898,
        "lng": -5.043717
      },
      {
        "lat": 54.911834,
        "lng": -5.043396
      },
      {
        "lat": 54.911783,
        "lng": -5.043431
      },
      {
        "lat": 54.911715,
        "lng": -5.043477
      },
      {
        "lat": 54.911631,
        "lng": -5.043509
      },
      {
        "lat": 54.911497,
        "lng": -5.043501
      },
      {
        "lat": 54.911143,
        "lng": -5.043315
      },
      {
        "lat": 54.910962,
        "lng": -5.043221
      },
      {
        "lat": 54.910477,
        "lng": -5.042894
      },
      {
        "lat": 54.910363,
        "lng": -5.042817
      },
      {
        "lat": 54.90962,
        "lng": -5.042493
      },
      {
        "lat": 54.909505,
        "lng": -5.042425
      },
      {
        "lat": 54.909456,
        "lng": -5.042594
      },
      {
        "lat": 54.909155,
        "lng": -5.04355
      },
      {
        "lat": 54.90913,
        "lng": -5.043641
      },
      {
        "lat": 54.908943,
        "lng": -5.044213
      },
      {
        "lat": 54.908883,
        "lng": -5.044396
      },
      {
        "lat": 54.908764,
        "lng": -5.044763
      },
      {
        "lat": 54.908689,
        "lng": -5.044811
      },
      {
        "lat": 54.908623,
        "lng": -5.044751
      },
      {
        "lat": 54.908396,
        "lng": -5.044041
      },
      {
        "lat": 54.908161,
        "lng": -5.043428
      },
      {
        "lat": 54.907964,
        "lng": -5.042973
      },
      {
        "lat": 54.907871,
        "lng": -5.042889
      },
      {
        "lat": 54.907329,
        "lng": -5.042509
      },
      {
        "lat": 54.907242,
        "lng": -5.042334
      },
      {
        "lat": 54.906975,
        "lng": -5.041721
      },
      {
        "lat": 54.906689,
        "lng": -5.042103
      },
      {
        "lat": 54.906598,
        "lng": -5.042179
      },
      {
        "lat": 54.906458,
        "lng": -5.042259
      },
      {
        "lat": 54.906274,
        "lng": -5.042364
      },
      {
        "lat": 54.906174,
        "lng": -5.041835
      },
      {
        "lat": 54.906116,
        "lng": -5.041657
      },
      {
        "lat": 54.905937,
        "lng": -5.041279
      },
      {
        "lat": 54.905451,
        "lng": -5.04025
      },
      {
        "lat": 54.905371,
        "lng": -5.040132
      },
      {
        "lat": 54.905103,
        "lng": -5.039871
      },
      {
        "lat": 54.904904,
        "lng": -5.040524
      },
      {
        "lat": 54.904712,
        "lng": -5.041151
      },
      {
        "lat": 54.904569,
        "lng": -5.041154
      },
      {
        "lat": 54.904524,
        "lng": -5.041131
      },
      {
        "lat": 54.904462,
        "lng": -5.041052
      },
      {
        "lat": 54.904298,
        "lng": -5.040725
      },
      {
        "lat": 54.904193,
        "lng": -5.040633
      },
      {
        "lat": 54.904318,
        "lng": -5.040228
      },
      {
        "lat": 54.904819,
        "lng": -5.0386
      },
      {
        "lat": 54.905071,
        "lng": -5.037809
      },
      {
        "lat": 54.905118,
        "lng": -5.037616
      },
      {
        "lat": 54.905156,
        "lng": -5.037451
      },
      {
        "lat": 54.905234,
        "lng": -5.036696
      },
      {
        "lat": 54.90523,
        "lng": -5.036432
      },
      {
        "lat": 54.905212,
        "lng": -5.036141
      },
      {
        "lat": 54.905192,
        "lng": -5.035942
      },
      {
        "lat": 54.905196,
        "lng": -5.035877
      },
      {
        "lat": 54.905207,
        "lng": -5.035814
      },
      {
        "lat": 54.905221,
        "lng": -5.035762
      },
      {
        "lat": 54.90524,
        "lng": -5.035715
      },
      {
        "lat": 54.905265,
        "lng": -5.035658
      },
      {
        "lat": 54.905286,
        "lng": -5.03561
      },
      {
        "lat": 54.904751,
        "lng": -5.034628
      },
      {
        "lat": 54.904583,
        "lng": -5.034332
      },
      {
        "lat": 54.904517,
        "lng": -5.034199
      },
      {
        "lat": 54.904455,
        "lng": -5.03406
      },
      {
        "lat": 54.904429,
        "lng": -5.033992
      },
      {
        "lat": 54.904398,
        "lng": -5.033914
      },
      {
        "lat": 54.904346,
        "lng": -5.033763
      },
      {
        "lat": 54.904297,
        "lng": -5.033603
      },
      {
        "lat": 54.90428,
        "lng": -5.033536
      },
      {
        "lat": 54.904254,
        "lng": -5.033438
      },
      {
        "lat": 54.904216,
        "lng": -5.033262
      },
      {
        "lat": 54.904171,
        "lng": -5.033016
      },
      {
        "lat": 54.904154,
        "lng": -5.032914
      },
      {
        "lat": 54.90413,
        "lng": -5.032758
      },
      {
        "lat": 54.90411,
        "lng": -5.032593
      },
      {
        "lat": 54.904142,
        "lng": -5.032581
      },
      {
        "lat": 54.90418,
        "lng": -5.032566
      },
      {
        "lat": 54.904274,
        "lng": -5.032493
      },
      {
        "lat": 54.904438,
        "lng": -5.032312
      },
      {
        "lat": 54.904468,
        "lng": -5.032277
      },
      {
        "lat": 54.90449,
        "lng": -5.032226
      },
      {
        "lat": 54.904499,
        "lng": -5.032185
      },
      {
        "lat": 54.904651,
        "lng": -5.03147
      },
      {
        "lat": 54.904674,
        "lng": -5.03136
      },
      {
        "lat": 54.904697,
        "lng": -5.031284
      },
      {
        "lat": 54.904731,
        "lng": -5.031172
      },
      {
        "lat": 54.904748,
        "lng": -5.031064
      },
      {
        "lat": 54.904749,
        "lng": -5.030693
      },
      {
        "lat": 54.904738,
        "lng": -5.030553
      },
      {
        "lat": 54.904733,
        "lng": -5.030486
      },
      {
        "lat": 54.904731,
        "lng": -5.030456
      },
      {
        "lat": 54.904732,
        "lng": -5.030398
      },
      {
        "lat": 54.904739,
        "lng": -5.030342
      },
      {
        "lat": 54.904743,
        "lng": -5.030325
      },
      {
        "lat": 54.904751,
        "lng": -5.030289
      },
      {
        "lat": 54.904767,
        "lng": -5.03024
      },
      {
        "lat": 54.904741,
        "lng": -5.030227
      },
      {
        "lat": 54.904718,
        "lng": -5.030201
      },
      {
        "lat": 54.9047,
        "lng": -5.030165
      },
      {
        "lat": 54.904689,
        "lng": -5.030121
      },
      {
        "lat": 54.904654,
        "lng": -5.029837
      },
      {
        "lat": 54.904623,
        "lng": -5.02946
      },
      {
        "lat": 54.904591,
        "lng": -5.02895
      },
      {
        "lat": 54.904588,
        "lng": -5.028881
      },
      {
        "lat": 54.904572,
        "lng": -5.028441
      },
      {
        "lat": 54.904569,
        "lng": -5.028221
      },
      {
        "lat": 54.90459,
        "lng": -5.028017
      },
      {
        "lat": 54.904611,
        "lng": -5.0278
      },
      {
        "lat": 54.904664,
        "lng": -5.027234
      },
      {
        "lat": 54.904619,
        "lng": -5.026921
      },
      {
        "lat": 54.904604,
        "lng": -5.026702
      },
      {
        "lat": 54.904603,
        "lng": -5.026674
      },
      {
        "lat": 54.904604,
        "lng": -5.026595
      },
      {
        "lat": 54.904605,
        "lng": -5.026353
      },
      {
        "lat": 54.90462,
        "lng": -5.026225
      },
      {
        "lat": 54.904625,
        "lng": -5.026182
      },
      {
        "lat": 54.904632,
        "lng": -5.026116
      },
      {
        "lat": 54.904641,
        "lng": -5.025874
      },
      {
        "lat": 54.90465,
        "lng": -5.025721
      },
      {
        "lat": 54.904666,
        "lng": -5.025612
      },
      {
        "lat": 54.904701,
        "lng": -5.025361
      },
      {
        "lat": 54.90477,
        "lng": -5.024912
      },
      {
        "lat": 54.904852,
        "lng": -5.024565
      },
      {
        "lat": 54.904936,
        "lng": -5.024236
      },
      {
        "lat": 54.904958,
        "lng": -5.024097
      },
      {
        "lat": 54.904403,
        "lng": -5.023778
      },
      {
        "lat": 54.904093,
        "lng": -5.023604
      },
      {
        "lat": 54.90397,
        "lng": -5.023532
      },
      {
        "lat": 54.903836,
        "lng": -5.023513
      },
      {
        "lat": 54.903789,
        "lng": -5.023509
      },
      {
        "lat": 54.903699,
        "lng": -5.023501
      },
      {
        "lat": 54.903545,
        "lng": -5.023487
      },
      {
        "lat": 54.903509,
        "lng": -5.023484
      },
      {
        "lat": 54.903474,
        "lng": -5.02347
      },
      {
        "lat": 54.903441,
        "lng": -5.023442
      },
      {
        "lat": 54.903413,
        "lng": -5.023406
      },
      {
        "lat": 54.90339,
        "lng": -5.023362
      },
      {
        "lat": 54.903372,
        "lng": -5.02331
      },
      {
        "lat": 54.903346,
        "lng": -5.023145
      },
      {
        "lat": 54.903312,
        "lng": -5.023164
      },
      {
        "lat": 54.903278,
        "lng": -5.023183
      },
      {
        "lat": 54.903236,
        "lng": -5.023191
      },
      {
        "lat": 54.902806,
        "lng": -5.023185
      },
      {
        "lat": 54.902597,
        "lng": -5.023182
      },
      {
        "lat": 54.902562,
        "lng": -5.023181
      },
      {
        "lat": 54.902494,
        "lng": -5.02318
      },
      {
        "lat": 54.902478,
        "lng": -5.02318
      },
      {
        "lat": 54.90234,
        "lng": -5.023178
      },
      {
        "lat": 54.902195,
        "lng": -5.023176
      },
      {
        "lat": 54.902032,
        "lng": -5.023173
      },
      {
        "lat": 54.901931,
        "lng": -5.023172
      },
      {
        "lat": 54.901839,
        "lng": -5.02317
      },
      {
        "lat": 54.901802,
        "lng": -5.02317
      },
      {
        "lat": 54.90168,
        "lng": -5.023168
      },
      {
        "lat": 54.901653,
        "lng": -5.023168
      },
      {
        "lat": 54.901604,
        "lng": -5.023167
      },
      {
        "lat": 54.900975,
        "lng": -5.023157
      },
      {
        "lat": 54.900787,
        "lng": -5.023154
      },
      {
        "lat": 54.90045,
        "lng": -5.023142
      },
      {
        "lat": 54.900355,
        "lng": -5.023139
      },
      {
        "lat": 54.900247,
        "lng": -5.023135
      },
      {
        "lat": 54.900075,
        "lng": -5.023129
      },
      {
        "lat": 54.899955,
        "lng": -5.023125
      },
      {
        "lat": 54.89984,
        "lng": -5.02312
      },
      {
        "lat": 54.899563,
        "lng": -5.023111
      },
      {
        "lat": 54.899558,
        "lng": -5.02311
      },
      {
        "lat": 54.899358,
        "lng": -5.023103
      },
      {
        "lat": 54.89909,
        "lng": -5.023094
      },
      {
        "lat": 54.899009,
        "lng": -5.023091
      },
      {
        "lat": 54.898843,
        "lng": -5.023085
      },
      {
        "lat": 54.898576,
        "lng": -5.023076
      },
      {
        "lat": 54.898559,
        "lng": -5.023075
      },
      {
        "lat": 54.898075,
        "lng": -5.023052
      },
      {
        "lat": 54.898025,
        "lng": -5.023052
      },
      {
        "lat": 54.897828,
        "lng": -5.023041
      },
      {
        "lat": 54.897764,
        "lng": -5.023038
      },
      {
        "lat": 54.897737,
        "lng": -5.023017
      },
      {
        "lat": 54.897708,
        "lng": -5.023009
      },
      {
        "lat": 54.897679,
        "lng": -5.023016
      },
      {
        "lat": 54.897652,
        "lng": -5.023035
      },
      {
        "lat": 54.897635,
        "lng": -5.023057
      },
      {
        "lat": 54.897621,
        "lng": -5.023084
      },
      {
        "lat": 54.897298,
        "lng": -5.023079
      },
      {
        "lat": 54.897142,
        "lng": -5.023056
      },
      {
        "lat": 54.897109,
        "lng": -5.023051
      },
      {
        "lat": 54.896917,
        "lng": -5.023045
      },
      {
        "lat": 54.896799,
        "lng": -5.023041
      },
      {
        "lat": 54.896783,
        "lng": -5.02304
      },
      {
        "lat": 54.896367,
        "lng": -5.023027
      },
      {
        "lat": 54.896194,
        "lng": -5.023022
      },
      {
        "lat": 54.896093,
        "lng": -5.023019
      },
      {
        "lat": 54.895958,
        "lng": -5.023014
      },
      {
        "lat": 54.895801,
        "lng": -5.02301
      },
      {
        "lat": 54.895617,
        "lng": -5.022978
      },
      {
        "lat": 54.895528,
        "lng": -5.022918
      },
      {
        "lat": 54.895398,
        "lng": -5.022931
      },
      {
        "lat": 54.89456,
        "lng": -5.022904
      },
      {
        "lat": 54.894487,
        "lng": -5.022902
      },
      {
        "lat": 54.893047,
        "lng": -5.022842
      },
      {
        "lat": 54.89254,
        "lng": -5.022822
      },
      {
        "lat": 54.892528,
        "lng": -5.023219
      },
      {
        "lat": 54.89253,
        "lng": -5.023323
      },
      {
        "lat": 54.892534,
        "lng": -5.023524
      },
      {
        "lat": 54.892576,
        "lng": -5.023946
      },
      {
        "lat": 54.892643,
        "lng": -5.024334
      },
      {
        "lat": 54.892656,
        "lng": -5.024407
      },
      {
        "lat": 54.892845,
        "lng": -5.025222
      },
      {
        "lat": 54.892891,
        "lng": -5.025371
      },
      {
        "lat": 54.892982,
        "lng": -5.025669
      },
      {
        "lat": 54.893032,
        "lng": -5.025831
      },
      {
        "lat": 54.89309,
        "lng": -5.02601
      },
      {
        "lat": 54.893208,
        "lng": -5.026376
      },
      {
        "lat": 54.893351,
        "lng": -5.026714
      },
      {
        "lat": 54.893661,
        "lng": -5.027455
      },
      {
        "lat": 54.893605,
        "lng": -5.027524
      },
      {
        "lat": 54.893243,
        "lng": -5.028043
      },
      {
        "lat": 54.89309,
        "lng": -5.028283
      },
      {
        "lat": 54.893001,
        "lng": -5.028463
      },
      {
        "lat": 54.892947,
        "lng": -5.028639
      },
      {
        "lat": 54.892905,
        "lng": -5.028825
      },
      {
        "lat": 54.892881,
        "lng": -5.029074
      },
      {
        "lat": 54.892878,
        "lng": -5.029325
      },
      {
        "lat": 54.892897,
        "lng": -5.029542
      },
      {
        "lat": 54.892947,
        "lng": -5.029773
      },
      {
        "lat": 54.892972,
        "lng": -5.02983
      },
      {
        "lat": 54.893079,
        "lng": -5.030071
      },
      {
        "lat": 54.893507,
        "lng": -5.030862
      },
      {
        "lat": 54.893653,
        "lng": -5.031137
      },
      {
        "lat": 54.893775,
        "lng": -5.031276
      },
      {
        "lat": 54.893885,
        "lng": -5.031358
      },
      {
        "lat": 54.894022,
        "lng": -5.031392
      },
      {
        "lat": 54.89406,
        "lng": -5.031394
      },
      {
        "lat": 54.894116,
        "lng": -5.031396
      },
      {
        "lat": 54.894387,
        "lng": -5.031338
      },
      {
        "lat": 54.894542,
        "lng": -5.031308
      },
      {
        "lat": 54.894667,
        "lng": -5.031319
      },
      {
        "lat": 54.894935,
        "lng": -5.031304
      },
      {
        "lat": 54.895062,
        "lng": -5.031223
      },
      {
        "lat": 54.895299,
        "lng": -5.031932
      },
      {
        "lat": 54.895284,
        "lng": -5.031952
      },
      {
        "lat": 54.895266,
        "lng": -5.031996
      },
      {
        "lat": 54.895257,
        "lng": -5.032057
      },
      {
        "lat": 54.89526,
        "lng": -5.032099
      },
      {
        "lat": 54.895266,
        "lng": -5.032128
      },
      {
        "lat": 54.895278,
        "lng": -5.032161
      },
      {
        "lat": 54.895308,
        "lng": -5.032201
      },
      {
        "lat": 54.895342,
        "lng": -5.032216
      },
      {
        "lat": 54.895379,
        "lng": -5.032203
      },
      {
        "lat": 54.895395,
        "lng": -5.03219
      },
      {
        "lat": 54.895516,
        "lng": -5.032561
      },
      {
        "lat": 54.895811,
        "lng": -5.033455
      },
      {
        "lat": 54.896046,
        "lng": -5.034208
      },
      {
        "lat": 54.896247,
        "lng": -5.034686
      },
      {
        "lat": 54.896631,
        "lng": -5.035333
      },
      {
        "lat": 54.896644,
        "lng": -5.035352
      },
      {
        "lat": 54.897112,
        "lng": -5.036042
      },
      {
        "lat": 54.89721,
        "lng": -5.036164
      },
      {
        "lat": 54.897282,
        "lng": -5.036205
      },
      {
        "lat": 54.897276,
        "lng": -5.036263
      },
      {
        "lat": 54.897287,
        "lng": -5.036319
      },
      {
        "lat": 54.89731,
        "lng": -5.036357
      },
      {
        "lat": 54.89735,
        "lng": -5.036374
      },
      {
        "lat": 54.897388,
        "lng": -5.036349
      },
      {
        "lat": 54.897411,
        "lng": -5.036296
      },
      {
        "lat": 54.897551,
        "lng": -5.036421
      },
      {
        "lat": 54.89772,
        "lng": -5.036494
      },
      {
        "lat": 54.897935,
        "lng": -5.036518
      },
      {
        "lat": 54.898142,
        "lng": -5.036482
      },
      {
        "lat": 54.898297,
        "lng": -5.036415
      },
      {
        "lat": 54.898574,
        "lng": -5.036254
      },
      {
        "lat": 54.899043,
        "lng": -5.035959
      },
      {
        "lat": 54.899133,
        "lng": -5.035903
      },
      {
        "lat": 54.899456,
        "lng": -5.035705
      },
      {
        "lat": 54.899514,
        "lng": -5.035643
      },
      {
        "lat": 54.89955,
        "lng": -5.035574
      },
      {
        "lat": 54.899574,
        "lng": -5.035469
      },
      {
        "lat": 54.899578,
        "lng": -5.035385
      },
      {
        "lat": 54.899567,
        "lng": -5.035293
      },
      {
        "lat": 54.899532,
        "lng": -5.035192
      },
      {
        "lat": 54.89927,
        "lng": -5.034796
      },
      {
        "lat": 54.899097,
        "lng": -5.034463
      },
      {
        "lat": 54.89891,
        "lng": -5.034011
      },
      {
        "lat": 54.898778,
        "lng": -5.033629
      },
      {
        "lat": 54.89858,
        "lng": -5.032859
      },
      {
        "lat": 54.898223,
        "lng": -5.031221
      },
      {
        "lat": 54.898053,
        "lng": -5.030449
      },
      {
        "lat": 54.897726,
        "lng": -5.028922
      },
      {
        "lat": 54.897752,
        "lng": -5.028654
      },
      {
        "lat": 54.897773,
        "lng": -5.028491
      },
      {
        "lat": 54.897804,
        "lng": -5.028285
      },
      {
        "lat": 54.897832,
        "lng": -5.028026
      },
      {
        "lat": 54.897821,
        "lng": -5.027846
      },
      {
        "lat": 54.897802,
        "lng": -5.027565
      },
      {
        "lat": 54.897787,
        "lng": -5.027343
      },
      {
        "lat": 54.897652,
        "lng": -5.025096
      },
      {
        "lat": 54.897652,
        "lng": -5.024861
      },
      {
        "lat": 54.89767,
        "lng": -5.024704
      },
      {
        "lat": 54.897694,
        "lng": -5.024577
      },
      {
        "lat": 54.897757,
        "lng": -5.024375
      },
      {
        "lat": 54.898095,
        "lng": -5.023589
      },
      {
        "lat": 54.898014,
        "lng": -5.023535
      },
      {
        "lat": 54.897846,
        "lng": -5.023323
      },
      {
        "lat": 54.897806,
        "lng": -5.023271
      },
      {
        "lat": 54.897813,
        "lng": -5.023226
      },
      {
        "lat": 54.897814,
        "lng": -5.023171
      },
      {
        "lat": 54.897805,
        "lng": -5.023119
      },
      {
        "lat": 54.897788,
        "lng": -5.023073
      },
      {
        "lat": 54.897764,
        "lng": -5.023038
      },
      {
        "lat": 54.897737,
        "lng": -5.023017
      },
      {
        "lat": 54.897708,
        "lng": -5.023009
      },
      {
        "lat": 54.897679,
        "lng": -5.023016
      },
      {
        "lat": 54.897652,
        "lng": -5.023035
      },
      {
        "lat": 54.897635,
        "lng": -5.023057
      },
      {
        "lat": 54.897621,
        "lng": -5.023084
      },
      {
        "lat": 54.897607,
        "lng": -5.023128
      },
      {
        "lat": 54.8976,
        "lng": -5.023177
      },
      {
        "lat": 54.897601,
        "lng": -5.023227
      },
      {
        "lat": 54.897609,
        "lng": -5.023275
      },
      {
        "lat": 54.897627,
        "lng": -5.023323
      },
      {
        "lat": 54.897653,
        "lng": -5.023359
      },
      {
        "lat": 54.897683,
        "lng": -5.02338
      },
      {
        "lat": 54.898014,
        "lng": -5.023535
      },
      {
        "lat": 54.898095,
        "lng": -5.023589
      },
      {
        "lat": 54.89785,
        "lng": -5.02416
      },
      {
        "lat": 54.897757,
        "lng": -5.024375
      },
      {
        "lat": 54.897714,
        "lng": -5.024514
      },
      {
        "lat": 54.897694,
        "lng": -5.024577
      },
      {
        "lat": 54.89767,
        "lng": -5.024704
      },
      {
        "lat": 54.897652,
        "lng": -5.024861
      },
      {
        "lat": 54.897652,
        "lng": -5.025096
      },
      {
        "lat": 54.897771,
        "lng": -5.027082
      },
      {
        "lat": 54.897787,
        "lng": -5.027343
      },
      {
        "lat": 54.897802,
        "lng": -5.027565
      },
      {
        "lat": 54.897821,
        "lng": -5.027846
      },
      {
        "lat": 54.898235,
        "lng": -5.02776
      },
      {
        "lat": 54.898551,
        "lng": -5.027694
      },
      {
        "lat": 54.898622,
        "lng": -5.027654
      },
      {
        "lat": 54.898973,
        "lng": -5.028907
      },
      {
        "lat": 54.899103,
        "lng": -5.02942
      },
      {
        "lat": 54.899135,
        "lng": -5.029549
      },
      {
        "lat": 54.899538,
        "lng": -5.031174
      },
      {
        "lat": 54.899577,
        "lng": -5.031387
      },
      {
        "lat": 54.899583,
        "lng": -5.031439
      },
      {
        "lat": 54.899673,
        "lng": -5.032207
      },
      {
        "lat": 54.899186,
        "lng": -5.032451
      },
      {
        "lat": 54.899142,
        "lng": -5.032531
      },
      {
        "lat": 54.899126,
        "lng": -5.032606
      },
      {
        "lat": 54.899135,
        "lng": -5.032719
      },
      {
        "lat": 54.899159,
        "lng": -5.032906
      },
      {
        "lat": 54.899251,
        "lng": -5.033618
      },
      {
        "lat": 54.89891,
        "lng": -5.034011
      },
      {
        "lat": 54.899079,
        "lng": -5.034419
      },
      {
        "lat": 54.899097,
        "lng": -5.034463
      },
      {
        "lat": 54.89927,
        "lng": -5.034796
      },
      {
        "lat": 54.899532,
        "lng": -5.035192
      },
      {
        "lat": 54.899567,
        "lng": -5.035293
      },
      {
        "lat": 54.899578,
        "lng": -5.035385
      },
      {
        "lat": 54.899574,
        "lng": -5.035469
      },
      {
        "lat": 54.899705,
        "lng": -5.035525
      },
      {
        "lat": 54.89989,
        "lng": -5.035544
      },
      {
        "lat": 54.900172,
        "lng": -5.035621
      },
      {
        "lat": 54.900446,
        "lng": -5.035664
      },
      {
        "lat": 54.900469,
        "lng": -5.036237
      },
      {
        "lat": 54.900516,
        "lng": -5.036524
      },
      {
        "lat": 54.900586,
        "lng": -5.036706
      },
      {
        "lat": 54.900701,
        "lng": -5.036856
      },
      {
        "lat": 54.900834,
        "lng": -5.036942
      },
      {
        "lat": 54.900911,
        "lng": -5.036959
      },
      {
        "lat": 54.900996,
        "lng": -5.036936
      },
      {
        "lat": 54.901017,
        "lng": -5.036931
      },
      {
        "lat": 54.901213,
        "lng": -5.036796
      },
      {
        "lat": 54.902161,
        "lng": -5.035907
      },
      {
        "lat": 54.902172,
        "lng": -5.035938
      },
      {
        "lat": 54.902217,
        "lng": -5.036068
      },
      {
        "lat": 54.902282,
        "lng": -5.036126
      },
      {
        "lat": 54.902359,
        "lng": -5.036171
      },
      {
        "lat": 54.902452,
        "lng": -5.036175
      },
      {
        "lat": 54.902532,
        "lng": -5.036138
      },
      {
        "lat": 54.902699,
        "lng": -5.035926
      },
      {
        "lat": 54.902944,
        "lng": -5.036261
      },
      {
        "lat": 54.903035,
        "lng": -5.036321
      },
      {
        "lat": 54.903314,
        "lng": -5.036381
      },
      {
        "lat": 54.903402,
        "lng": -5.036437
      },
      {
        "lat": 54.904093,
        "lng": -5.037202
      },
      {
        "lat": 54.904117,
        "lng": -5.037228
      },
      {
        "lat": 54.904298,
        "lng": -5.037382
      },
      {
        "lat": 54.904406,
        "lng": -5.037451
      },
      {
        "lat": 54.904549,
        "lng": -5.037491
      },
      {
        "lat": 54.904871,
        "lng": -5.037592
      },
      {
        "lat": 54.904982,
        "lng": -5.037575
      },
      {
        "lat": 54.905118,
        "lng": -5.037616
      },
      {
        "lat": 54.905156,
        "lng": -5.037451
      },
      {
        "lat": 54.905234,
        "lng": -5.036696
      },
      {
        "lat": 54.90523,
        "lng": -5.036432
      },
      {
        "lat": 54.905212,
        "lng": -5.036141
      },
      {
        "lat": 54.905192,
        "lng": -5.035942
      },
      {
        "lat": 54.905196,
        "lng": -5.035877
      },
      {
        "lat": 54.905207,
        "lng": -5.035814
      },
      {
        "lat": 54.905221,
        "lng": -5.035762
      },
      {
        "lat": 54.90524,
        "lng": -5.035715
      },
      {
        "lat": 54.905265,
        "lng": -5.035658
      },
      {
        "lat": 54.905286,
        "lng": -5.03561
      },
      {
        "lat": 54.904751,
        "lng": -5.034628
      },
      {
        "lat": 54.904583,
        "lng": -5.034332
      },
      {
        "lat": 54.904517,
        "lng": -5.034199
      },
      {
        "lat": 54.904455,
        "lng": -5.03406
      },
      {
        "lat": 54.904429,
        "lng": -5.033992
      },
      {
        "lat": 54.904398,
        "lng": -5.033914
      },
      {
        "lat": 54.904346,
        "lng": -5.033763
      },
      {
        "lat": 54.904297,
        "lng": -5.033603
      },
      {
        "lat": 54.90428,
        "lng": -5.033536
      },
      {
        "lat": 54.904254,
        "lng": -5.033438
      },
      {
        "lat": 54.904216,
        "lng": -5.033262
      },
      {
        "lat": 54.904171,
        "lng": -5.033016
      },
      {
        "lat": 54.904154,
        "lng": -5.032914
      },
      {
        "lat": 54.90413,
        "lng": -5.032758
      },
      {
        "lat": 54.90411,
        "lng": -5.032593
      },
      {
        "lat": 54.904142,
        "lng": -5.032581
      },
      {
        "lat": 54.90418,
        "lng": -5.032566
      },
      {
        "lat": 54.904274,
        "lng": -5.032493
      },
      {
        "lat": 54.904438,
        "lng": -5.032312
      },
      {
        "lat": 54.904468,
        "lng": -5.032277
      },
      {
        "lat": 54.90449,
        "lng": -5.032226
      },
      {
        "lat": 54.904499,
        "lng": -5.032185
      },
      {
        "lat": 54.904651,
        "lng": -5.03147
      },
      {
        "lat": 54.904674,
        "lng": -5.03136
      },
      {
        "lat": 54.904697,
        "lng": -5.031284
      },
      {
        "lat": 54.904731,
        "lng": -5.031172
      },
      {
        "lat": 54.904748,
        "lng": -5.031064
      },
      {
        "lat": 54.904749,
        "lng": -5.030693
      },
      {
        "lat": 54.904738,
        "lng": -5.030553
      },
      {
        "lat": 54.904733,
        "lng": -5.030486
      },
      {
        "lat": 54.904731,
        "lng": -5.030456
      },
      {
        "lat": 54.904732,
        "lng": -5.030398
      },
      {
        "lat": 54.904739,
        "lng": -5.030342
      },
      {
        "lat": 54.904743,
        "lng": -5.030325
      },
      {
        "lat": 54.904751,
        "lng": -5.030289
      },
      {
        "lat": 54.904767,
        "lng": -5.03024
      },
      {
        "lat": 54.904741,
        "lng": -5.030227
      },
      {
        "lat": 54.904718,
        "lng": -5.030201
      },
      {
        "lat": 54.9047,
        "lng": -5.030165
      },
      {
        "lat": 54.904689,
        "lng": -5.030121
      },
      {
        "lat": 54.904654,
        "lng": -5.029837
      },
      {
        "lat": 54.904623,
        "lng": -5.02946
      },
      {
        "lat": 54.904591,
        "lng": -5.02895
      },
      {
        "lat": 54.904588,
        "lng": -5.028881
      },
      {
        "lat": 54.904572,
        "lng": -5.028441
      },
      {
        "lat": 54.904569,
        "lng": -5.028221
      },
      {
        "lat": 54.90459,
        "lng": -5.028017
      },
      {
        "lat": 54.904611,
        "lng": -5.0278
      },
      {
        "lat": 54.904664,
        "lng": -5.027234
      },
      {
        "lat": 54.904619,
        "lng": -5.026921
      },
      {
        "lat": 54.904604,
        "lng": -5.026702
      },
      {
        "lat": 54.904603,
        "lng": -5.026674
      },
      {
        "lat": 54.904604,
        "lng": -5.026595
      },
      {
        "lat": 54.904605,
        "lng": -5.026353
      },
      {
        "lat": 54.90462,
        "lng": -5.026225
      },
      {
        "lat": 54.904625,
        "lng": -5.026182
      },
      {
        "lat": 54.904632,
        "lng": -5.026116
      },
      {
        "lat": 54.904641,
        "lng": -5.025874
      },
      {
        "lat": 54.90465,
        "lng": -5.025721
      },
      {
        "lat": 54.904666,
        "lng": -5.025612
      },
      {
        "lat": 54.904701,
        "lng": -5.025361
      },
      {
        "lat": 54.90477,
        "lng": -5.024912
      },
      {
        "lat": 54.904852,
        "lng": -5.024565
      },
      {
        "lat": 54.904936,
        "lng": -5.024236
      },
      {
        "lat": 54.904958,
        "lng": -5.024097
      },
      {
        "lat": 54.905,
        "lng": -5.024012
      },
      {
        "lat": 54.905173,
        "lng": -5.023749
      },
      {
        "lat": 54.905285,
        "lng": -5.023672
      },
      {
        "lat": 54.905362,
        "lng": -5.023592
      },
      {
        "lat": 54.905372,
        "lng": -5.0236
      },
      {
        "lat": 54.905407,
        "lng": -5.023613
      },
      {
        "lat": 54.905442,
        "lng": -5.02361
      },
      {
        "lat": 54.905475,
        "lng": -5.023589
      },
      {
        "lat": 54.905503,
        "lng": -5.023553
      },
      {
        "lat": 54.905525,
        "lng": -5.023504
      },
      {
        "lat": 54.905539,
        "lng": -5.023435
      },
      {
        "lat": 54.905539,
        "lng": -5.023368
      },
      {
        "lat": 54.90554,
        "lng": -5.023244
      },
      {
        "lat": 54.905543,
        "lng": -5.023198
      },
      {
        "lat": 54.905563,
        "lng": -5.02289
      },
      {
        "lat": 54.905579,
        "lng": -5.022748
      },
      {
        "lat": 54.9056,
        "lng": -5.022547
      },
      {
        "lat": 54.905675,
        "lng": -5.021846
      },
      {
        "lat": 54.905701,
        "lng": -5.021534
      },
      {
        "lat": 54.905699,
        "lng": -5.021401
      },
      {
        "lat": 54.905685,
        "lng": -5.021225
      },
      {
        "lat": 54.90568,
        "lng": -5.021188
      },
      {
        "lat": 54.905659,
        "lng": -5.02103
      },
      {
        "lat": 54.905636,
        "lng": -5.020884
      },
      {
        "lat": 54.905622,
        "lng": -5.020796
      },
      {
        "lat": 54.905514,
        "lng": -5.020363
      },
      {
        "lat": 54.905393,
        "lng": -5.019942
      },
      {
        "lat": 54.905342,
        "lng": -5.019683
      },
      {
        "lat": 54.905207,
        "lng": -5.018925
      },
      {
        "lat": 54.905174,
        "lng": -5.018736
      },
      {
        "lat": 54.905151,
        "lng": -5.018584
      },
      {
        "lat": 54.905141,
        "lng": -5.018483
      },
      {
        "lat": 54.905143,
        "lng": -5.018398
      },
      {
        "lat": 54.905149,
        "lng": -5.018326
      },
      {
        "lat": 54.905118,
        "lng": -5.018296
      },
      {
        "lat": 54.905053,
        "lng": -5.018233
      },
      {
        "lat": 54.904863,
        "lng": -5.018055
      },
      {
        "lat": 54.904719,
        "lng": -5.017926
      },
      {
        "lat": 54.904677,
        "lng": -5.017889
      },
      {
        "lat": 54.904563,
        "lng": -5.017805
      },
      {
        "lat": 54.904437,
        "lng": -5.017724
      },
      {
        "lat": 54.904297,
        "lng": -5.017658
      },
      {
        "lat": 54.904265,
        "lng": -5.017643
      },
      {
        "lat": 54.904247,
        "lng": -5.017637
      },
      {
        "lat": 54.904089,
        "lng": -5.017583
      },
      {
        "lat": 54.903846,
        "lng": -5.017521
      },
      {
        "lat": 54.903637,
        "lng": -5.017477
      },
      {
        "lat": 54.903509,
        "lng": -5.017458
      },
      {
        "lat": 54.903475,
        "lng": -5.017441
      },
      {
        "lat": 54.903504,
        "lng": -5.016518
      },
      {
        "lat": 54.903527,
        "lng": -5.015903
      },
      {
        "lat": 54.903536,
        "lng": -5.015677
      },
      {
        "lat": 54.903542,
        "lng": -5.015556
      },
      {
        "lat": 54.903558,
        "lng": -5.015102
      },
      {
        "lat": 54.903605,
        "lng": -5.013732
      },
      {
        "lat": 54.903622,
        "lng": -5.013332
      },
      {
        "lat": 54.903649,
        "lng": -5.012601
      },
      {
        "lat": 54.903718,
        "lng": -5.010737
      },
      {
        "lat": 54.903849,
        "lng": -5.007262
      },
      {
        "lat": 54.903867,
        "lng": -5.00688
      },
      {
        "lat": 54.903878,
        "lng": -5.006403
      },
      {
        "lat": 54.903948,
        "lng": -5.004319
      },
      {
        "lat": 54.90402,
        "lng": -5.002363
      },
      {
        "lat": 54.904043,
        "lng": -5.002123
      },
      {
        "lat": 54.904141,
        "lng": -5.001441
      },
      {
        "lat": 54.90422,
        "lng": -5.000935
      },
      {
        "lat": 54.904237,
        "lng": -5.00084
      },
      {
        "lat": 54.904389,
        "lng": -5.000978
      },
      {
        "lat": 54.904724,
        "lng": -5.001346
      },
      {
        "lat": 54.904891,
        "lng": -5.000911
      },
      {
        "lat": 54.905028,
        "lng": -5.000545
      },
      {
        "lat": 54.905163,
        "lng": -5.000184
      },
      {
        "lat": 54.905364,
        "lng": -4.999674
      },
      {
        "lat": 54.905435,
        "lng": -4.999588
      },
      {
        "lat": 54.905511,
        "lng": -4.999573
      },
      {
        "lat": 54.905594,
        "lng": -4.999605
      },
      {
        "lat": 54.906171,
        "lng": -5.00027
      },
      {
        "lat": 54.906407,
        "lng": -5.000538
      },
      {
        "lat": 54.90664,
        "lng": -5.000801
      },
      {
        "lat": 54.906649,
        "lng": -5.000812
      },
      {
        "lat": 54.907438,
        "lng": -5.00171
      },
      {
        "lat": 54.907099,
        "lng": -5.002963
      },
      {
        "lat": 54.906964,
        "lng": -5.003461
      },
      {
        "lat": 54.906872,
        "lng": -5.003801
      },
      {
        "lat": 54.906538,
        "lng": -5.00342
      },
      {
        "lat": 54.906321,
        "lng": -5.003988
      },
      {
        "lat": 54.906179,
        "lng": -5.005567
      },
      {
        "lat": 54.906084,
        "lng": -5.006673
      },
      {
        "lat": 54.906043,
        "lng": -5.007168
      },
      {
        "lat": 54.906022,
        "lng": -5.007415
      },
      {
        "lat": 54.906036,
        "lng": -5.007561
      },
      {
        "lat": 54.906082,
        "lng": -5.007696
      },
      {
        "lat": 54.906149,
        "lng": -5.007767
      },
      {
        "lat": 54.906888,
        "lng": -5.00794
      },
      {
        "lat": 54.906899,
        "lng": -5.007694
      },
      {
        "lat": 54.907026,
        "lng": -5.006896
      },
      {
        "lat": 54.90709,
        "lng": -5.00648
      },
      {
        "lat": 54.907182,
        "lng": -5.005884
      },
      {
        "lat": 54.907226,
        "lng": -5.005685
      },
      {
        "lat": 54.907397,
        "lng": -5.005224
      },
      {
        "lat": 54.907477,
        "lng": -5.005097
      },
      {
        "lat": 54.907599,
        "lng": -5.005335
      },
      {
        "lat": 54.907715,
        "lng": -5.005466
      },
      {
        "lat": 54.907922,
        "lng": -5.005575
      },
      {
        "lat": 54.908366,
        "lng": -5.005808
      },
      {
        "lat": 54.908776,
        "lng": -5.006021
      },
      {
        "lat": 54.908479,
        "lng": -5.006879
      },
      {
        "lat": 54.908328,
        "lng": -5.007313
      },
      {
        "lat": 54.907087,
        "lng": -5.011005
      },
      {
        "lat": 54.907051,
        "lng": -5.011138
      },
      {
        "lat": 54.906886,
        "lng": -5.011755
      },
      {
        "lat": 54.905814,
        "lng": -5.015771
      },
      {
        "lat": 54.90557,
        "lng": -5.016708
      },
      {
        "lat": 54.905491,
        "lng": -5.017014
      },
      {
        "lat": 54.905282,
        "lng": -5.017787
      },
      {
        "lat": 54.905218,
        "lng": -5.01803
      },
      {
        "lat": 54.905149,
        "lng": -5.018326
      },
      {
        "lat": 54.905118,
        "lng": -5.018296
      },
      {
        "lat": 54.905053,
        "lng": -5.018233
      },
      {
        "lat": 54.904863,
        "lng": -5.018055
      },
      {
        "lat": 54.904719,
        "lng": -5.017926
      },
      {
        "lat": 54.904677,
        "lng": -5.017889
      },
      {
        "lat": 54.904563,
        "lng": -5.017805
      },
      {
        "lat": 54.904437,
        "lng": -5.017724
      },
      {
        "lat": 54.904297,
        "lng": -5.017658
      },
      {
        "lat": 54.904265,
        "lng": -5.017643
      },
      {
        "lat": 54.904247,
        "lng": -5.017637
      },
      {
        "lat": 54.904089,
        "lng": -5.017583
      },
      {
        "lat": 54.903846,
        "lng": -5.017521
      },
      {
        "lat": 54.903637,
        "lng": -5.017477
      },
      {
        "lat": 54.903509,
        "lng": -5.017458
      },
      {
        "lat": 54.903475,
        "lng": -5.017453
      },
      {
        "lat": 54.903434,
        "lng": -5.017449
      },
      {
        "lat": 54.902868,
        "lng": -5.017392
      },
      {
        "lat": 54.902486,
        "lng": -5.017351
      },
      {
        "lat": 54.902057,
        "lng": -5.017305
      },
      {
        "lat": 54.90196,
        "lng": -5.017294
      },
      {
        "lat": 54.901615,
        "lng": -5.017257
      },
      {
        "lat": 54.901091,
        "lng": -5.017224
      },
      {
        "lat": 54.901049,
        "lng": -5.017226
      },
      {
        "lat": 54.901008,
        "lng": -5.017242
      },
      {
        "lat": 54.90097,
        "lng": -5.017273
      },
      {
        "lat": 54.900954,
        "lng": -5.01729
      },
      {
        "lat": 54.900936,
        "lng": -5.017316
      },
      {
        "lat": 54.900912,
        "lng": -5.017361
      },
      {
        "lat": 54.900893,
        "lng": -5.017412
      },
      {
        "lat": 54.900879,
        "lng": -5.017468
      },
      {
        "lat": 54.900871,
        "lng": -5.017527
      },
      {
        "lat": 54.900868,
        "lng": -5.017588
      },
      {
        "lat": 54.900865,
        "lng": -5.017773
      },
      {
        "lat": 54.900856,
        "lng": -5.018344
      },
      {
        "lat": 54.900854,
        "lng": -5.018446
      },
      {
        "lat": 54.900847,
        "lng": -5.018889
      },
      {
        "lat": 54.900842,
        "lng": -5.019146
      },
      {
        "lat": 54.900837,
        "lng": -5.019466
      },
      {
        "lat": 54.900827,
        "lng": -5.020025
      },
      {
        "lat": 54.900821,
        "lng": -5.020389
      },
      {
        "lat": 54.900819,
        "lng": -5.020537
      },
      {
        "lat": 54.900814,
        "lng": -5.020808
      },
      {
        "lat": 54.900805,
        "lng": -5.021343
      },
      {
        "lat": 54.900799,
        "lng": -5.021679
      },
      {
        "lat": 54.900788,
        "lng": -5.022351
      },
      {
        "lat": 54.900788,
        "lng": -5.022513
      },
      {
        "lat": 54.900787,
        "lng": -5.022976
      },
      {
        "lat": 54.900787,
        "lng": -5.023092
      },
      {
        "lat": 54.900787,
        "lng": -5.023154
      },
      {
        "lat": 54.90045,
        "lng": -5.023142
      },
      {
        "lat": 54.900355,
        "lng": -5.023139
      },
      {
        "lat": 54.900247,
        "lng": -5.023135
      },
      {
        "lat": 54.900075,
        "lng": -5.023129
      },
      {
        "lat": 54.899955,
        "lng": -5.023125
      },
      {
        "lat": 54.89984,
        "lng": -5.02312
      },
      {
        "lat": 54.899563,
        "lng": -5.023111
      },
      {
        "lat": 54.899558,
        "lng": -5.02311
      },
      {
        "lat": 54.899358,
        "lng": -5.023103
      },
      {
        "lat": 54.89909,
        "lng": -5.023094
      },
      {
        "lat": 54.899009,
        "lng": -5.023091
      },
      {
        "lat": 54.898843,
        "lng": -5.023085
      },
      {
        "lat": 54.898576,
        "lng": -5.023076
      },
      {
        "lat": 54.898559,
        "lng": -5.023075
      },
      {
        "lat": 54.898075,
        "lng": -5.023052
      },
      {
        "lat": 54.898025,
        "lng": -5.023052
      },
      {
        "lat": 54.897828,
        "lng": -5.023041
      },
      {
        "lat": 54.897764,
        "lng": -5.023038
      },
      {
        "lat": 54.897737,
        "lng": -5.023017
      },
      {
        "lat": 54.897708,
        "lng": -5.023009
      },
      {
        "lat": 54.897679,
        "lng": -5.023016
      },
      {
        "lat": 54.897652,
        "lng": -5.023035
      },
      {
        "lat": 54.897635,
        "lng": -5.023057
      },
      {
        "lat": 54.897621,
        "lng": -5.023084
      },
      {
        "lat": 54.897607,
        "lng": -5.023128
      },
      {
        "lat": 54.8976,
        "lng": -5.023177
      },
      {
        "lat": 54.897601,
        "lng": -5.023227
      },
      {
        "lat": 54.897609,
        "lng": -5.023275
      },
      {
        "lat": 54.897627,
        "lng": -5.023323
      },
      {
        "lat": 54.897653,
        "lng": -5.023359
      },
      {
        "lat": 54.897683,
        "lng": -5.02338
      },
      {
        "lat": 54.898014,
        "lng": -5.023535
      },
      {
        "lat": 54.898095,
        "lng": -5.023589
      },
      {
        "lat": 54.898658,
        "lng": -5.023995
      },
      {
        "lat": 54.898977,
        "lng": -5.024224
      },
      {
        "lat": 54.899081,
        "lng": -5.024299
      },
      {
        "lat": 54.899154,
        "lng": -5.024352
      },
      {
        "lat": 54.899374,
        "lng": -5.02451
      },
      {
        "lat": 54.899414,
        "lng": -5.024538
      },
      {
        "lat": 54.899506,
        "lng": -5.024605
      },
      {
        "lat": 54.899893,
        "lng": -5.024883
      },
      {
        "lat": 54.900143,
        "lng": -5.025063
      },
      {
        "lat": 54.900204,
        "lng": -5.025108
      },
      {
        "lat": 54.900299,
        "lng": -5.025179
      },
      {
        "lat": 54.900428,
        "lng": -5.025274
      },
      {
        "lat": 54.90054,
        "lng": -5.025358
      },
      {
        "lat": 54.900687,
        "lng": -5.025466
      },
      {
        "lat": 54.900708,
        "lng": -5.025482
      },
      {
        "lat": 54.900721,
        "lng": -5.025491
      },
      {
        "lat": 54.900997,
        "lng": -5.025691
      },
      {
        "lat": 54.901153,
        "lng": -5.025804
      },
      {
        "lat": 54.901224,
        "lng": -5.025856
      },
      {
        "lat": 54.901389,
        "lng": -5.025976
      },
      {
        "lat": 54.901486,
        "lng": -5.026046
      },
      {
        "lat": 54.901535,
        "lng": -5.02608
      },
      {
        "lat": 54.901714,
        "lng": -5.02621
      },
      {
        "lat": 54.901842,
        "lng": -5.026303
      },
      {
        "lat": 54.901969,
        "lng": -5.026395
      },
      {
        "lat": 54.902,
        "lng": -5.026418
      },
      {
        "lat": 54.902227,
        "lng": -5.026582
      },
      {
        "lat": 54.902427,
        "lng": -5.026727
      },
      {
        "lat": 54.902434,
        "lng": -5.026732
      },
      {
        "lat": 54.902576,
        "lng": -5.026833
      },
      {
        "lat": 54.902823,
        "lng": -5.02701
      },
      {
        "lat": 54.903119,
        "lng": -5.027222
      },
      {
        "lat": 54.903438,
        "lng": -5.027451
      },
      {
        "lat": 54.90357,
        "lng": -5.027545
      },
      {
        "lat": 54.90362,
        "lng": -5.027581
      },
      {
        "lat": 54.903696,
        "lng": -5.027635
      },
      {
        "lat": 54.90377,
        "lng": -5.027719
      },
      {
        "lat": 54.90388,
        "lng": -5.027796
      },
      {
        "lat": 54.904385,
        "lng": -5.028152
      },
      {
        "lat": 54.904569,
        "lng": -5.028221
      },
      {
        "lat": 54.90459,
        "lng": -5.028017
      },
      {
        "lat": 54.904611,
        "lng": -5.0278
      },
      {
        "lat": 54.904664,
        "lng": -5.027234
      },
      {
        "lat": 54.904619,
        "lng": -5.026921
      },
      {
        "lat": 54.904604,
        "lng": -5.026702
      },
      {
        "lat": 54.904603,
        "lng": -5.026674
      },
      {
        "lat": 54.904604,
        "lng": -5.026595
      },
      {
        "lat": 54.904605,
        "lng": -5.026353
      },
      {
        "lat": 54.90462,
        "lng": -5.026225
      },
      {
        "lat": 54.904632,
        "lng": -5.026116
      }
    ]
  }
}