{
  "line": "X19",
  "origin": "New South Glasgow Hospitals",
  "destination": "Easterhouse",
  "serviceCode": "X19",
  "routeData": {
    "totalDistance": 22276.799999999,
    "totalTime": 2383.799999999,
    "coordinates": [
      {
        "lat": 55.863088,
        "lng": -4.341613
      },
      {
        "lat": 55.863085,
        "lng": -4.341693
      },
      {
        "lat": 55.863081,
        "lng": -4.341785
      },
      {
        "lat": 55.863087,
        "lng": -4.342042
      },
      {
        "lat": 55.863242,
        "lng": -4.342572
      },
      {
        "lat": 55.863368,
        "lng": -4.343007
      },
      {
        "lat": 55.863633,
        "lng": -4.343917
      },
      {
        "lat": 55.863751,
        "lng": -4.344322
      },
      {
        "lat": 55.863717,
        "lng": -4.344352
      },
      {
        "lat": 55.863584,
        "lng": -4.344467
      },
      {
        "lat": 55.863539,
        "lng": -4.344506
      },
      {
        "lat": 55.863102,
        "lng": -4.344884
      },
      {
        "lat": 55.86281,
        "lng": -4.345136
      },
      {
        "lat": 55.862679,
        "lng": -4.34525
      },
      {
        "lat": 55.862501,
        "lng": -4.345404
      },
      {
        "lat": 55.861372,
        "lng": -4.346438
      },
      {
        "lat": 55.860923,
        "lng": -4.34683
      },
      {
        "lat": 55.86068,
        "lng": -4.34705
      },
      {
        "lat": 55.860266,
        "lng": -4.347433
      },
      {
        "lat": 55.859877,
        "lng": -4.347805
      },
      {
        "lat": 55.859786,
        "lng": -4.347877
      },
      {
        "lat": 55.85972,
        "lng": -4.347974
      },
      {
        "lat": 55.859819,
        "lng": -4.34824
      },
      {
        "lat": 55.85992,
        "lng": -4.348514
      },
      {
        "lat": 55.860021,
        "lng": -4.348774
      },
      {
        "lat": 55.860122,
        "lng": -4.349002
      },
      {
        "lat": 55.860235,
        "lng": -4.349221
      },
      {
        "lat": 55.860359,
        "lng": -4.349447
      },
      {
        "lat": 55.860484,
        "lng": -4.349653
      },
      {
        "lat": 55.860667,
        "lng": -4.349915
      },
      {
        "lat": 55.860751,
        "lng": -4.350044
      },
      {
        "lat": 55.860877,
        "lng": -4.35022
      },
      {
        "lat": 55.861063,
        "lng": -4.350482
      },
      {
        "lat": 55.861181,
        "lng": -4.350625
      },
      {
        "lat": 55.861315,
        "lng": -4.350778
      },
      {
        "lat": 55.861463,
        "lng": -4.35093
      },
      {
        "lat": 55.861621,
        "lng": -4.351078
      },
      {
        "lat": 55.861929,
        "lng": -4.351333
      },
      {
        "lat": 55.862043,
        "lng": -4.351426
      },
      {
        "lat": 55.862097,
        "lng": -4.351473
      },
      {
        "lat": 55.862147,
        "lng": -4.351519
      },
      {
        "lat": 55.862233,
        "lng": -4.35161
      },
      {
        "lat": 55.862302,
        "lng": -4.351687
      },
      {
        "lat": 55.862419,
        "lng": -4.351824
      },
      {
        "lat": 55.86254,
        "lng": -4.351978
      },
      {
        "lat": 55.862642,
        "lng": -4.352133
      },
      {
        "lat": 55.862828,
        "lng": -4.352457
      },
      {
        "lat": 55.862912,
        "lng": -4.352599
      },
      {
        "lat": 55.862976,
        "lng": -4.352689
      },
      {
        "lat": 55.863031,
        "lng": -4.352753
      },
      {
        "lat": 55.863159,
        "lng": -4.352879
      },
      {
        "lat": 55.863241,
        "lng": -4.352964
      },
      {
        "lat": 55.863273,
        "lng": -4.35301
      },
      {
        "lat": 55.863302,
        "lng": -4.353059
      },
      {
        "lat": 55.863325,
        "lng": -4.353106
      },
      {
        "lat": 55.863381,
        "lng": -4.35325
      },
      {
        "lat": 55.863404,
        "lng": -4.353312
      },
      {
        "lat": 55.863435,
        "lng": -4.353363
      },
      {
        "lat": 55.863479,
        "lng": -4.353408
      },
      {
        "lat": 55.863532,
        "lng": -4.353432
      },
      {
        "lat": 55.863568,
        "lng": -4.353433
      },
      {
        "lat": 55.863607,
        "lng": -4.353421
      },
      {
        "lat": 55.863639,
        "lng": -4.3534
      },
      {
        "lat": 55.863673,
        "lng": -4.353363
      },
      {
        "lat": 55.863693,
        "lng": -4.35333
      },
      {
        "lat": 55.863713,
        "lng": -4.353289
      },
      {
        "lat": 55.863737,
        "lng": -4.353212
      },
      {
        "lat": 55.863749,
        "lng": -4.353114
      },
      {
        "lat": 55.863741,
        "lng": -4.352981
      },
      {
        "lat": 55.86372,
        "lng": -4.352899
      },
      {
        "lat": 55.863746,
        "lng": -4.352649
      },
      {
        "lat": 55.86376,
        "lng": -4.352565
      },
      {
        "lat": 55.863812,
        "lng": -4.352432
      },
      {
        "lat": 55.864027,
        "lng": -4.352127
      },
      {
        "lat": 55.864146,
        "lng": -4.35197
      },
      {
        "lat": 55.864315,
        "lng": -4.351672
      },
      {
        "lat": 55.864522,
        "lng": -4.351401
      },
      {
        "lat": 55.865131,
        "lng": -4.350591
      },
      {
        "lat": 55.866793,
        "lng": -4.348359
      },
      {
        "lat": 55.867231,
        "lng": -4.347771
      },
      {
        "lat": 55.867506,
        "lng": -4.347371
      },
      {
        "lat": 55.867587,
        "lng": -4.347181
      },
      {
        "lat": 55.867648,
        "lng": -4.346971
      },
      {
        "lat": 55.867693,
        "lng": -4.346712
      },
      {
        "lat": 55.867706,
        "lng": -4.346453
      },
      {
        "lat": 55.86763,
        "lng": -4.346094
      },
      {
        "lat": 55.867098,
        "lng": -4.344242
      },
      {
        "lat": 55.867015,
        "lng": -4.343951
      },
      {
        "lat": 55.866475,
        "lng": -4.341923
      },
      {
        "lat": 55.866342,
        "lng": -4.341443
      },
      {
        "lat": 55.866197,
        "lng": -4.340918
      },
      {
        "lat": 55.865873,
        "lng": -4.339716
      },
      {
        "lat": 55.865819,
        "lng": -4.339516
      },
      {
        "lat": 55.865786,
        "lng": -4.339395
      },
      {
        "lat": 55.865774,
        "lng": -4.33934
      },
      {
        "lat": 55.865692,
        "lng": -4.33903
      },
      {
        "lat": 55.86528,
        "lng": -4.337481
      },
      {
        "lat": 55.865256,
        "lng": -4.337377
      },
      {
        "lat": 55.865203,
        "lng": -4.337146
      },
      {
        "lat": 55.864922,
        "lng": -4.335909
      },
      {
        "lat": 55.864858,
        "lng": -4.335609
      },
      {
        "lat": 55.864857,
        "lng": -4.335153
      },
      {
        "lat": 55.864847,
        "lng": -4.335068
      },
      {
        "lat": 55.864835,
        "lng": -4.334978
      },
      {
        "lat": 55.864804,
        "lng": -4.334795
      },
      {
        "lat": 55.864785,
        "lng": -4.334677
      },
      {
        "lat": 55.864722,
        "lng": -4.334336
      },
      {
        "lat": 55.864679,
        "lng": -4.334157
      },
      {
        "lat": 55.86462,
        "lng": -4.333953
      },
      {
        "lat": 55.864509,
        "lng": -4.333764
      },
      {
        "lat": 55.864491,
        "lng": -4.333681
      },
      {
        "lat": 55.864458,
        "lng": -4.333524
      },
      {
        "lat": 55.86444,
        "lng": -4.333415
      },
      {
        "lat": 55.864341,
        "lng": -4.332815
      },
      {
        "lat": 55.864328,
        "lng": -4.332692
      },
      {
        "lat": 55.864302,
        "lng": -4.332449
      },
      {
        "lat": 55.864268,
        "lng": -4.331644
      },
      {
        "lat": 55.864267,
        "lng": -4.331537
      },
      {
        "lat": 55.864254,
        "lng": -4.3311
      },
      {
        "lat": 55.86425,
        "lng": -4.331011
      },
      {
        "lat": 55.864244,
        "lng": -4.330868
      },
      {
        "lat": 55.864219,
        "lng": -4.33031
      },
      {
        "lat": 55.864185,
        "lng": -4.329392
      },
      {
        "lat": 55.864198,
        "lng": -4.329288
      },
      {
        "lat": 55.864191,
        "lng": -4.329079
      },
      {
        "lat": 55.864186,
        "lng": -4.328968
      },
      {
        "lat": 55.864172,
        "lng": -4.328853
      },
      {
        "lat": 55.864167,
        "lng": -4.328801
      },
      {
        "lat": 55.864144,
        "lng": -4.328688
      },
      {
        "lat": 55.864088,
        "lng": -4.328561
      },
      {
        "lat": 55.864016,
        "lng": -4.328442
      },
      {
        "lat": 55.863983,
        "lng": -4.328336
      },
      {
        "lat": 55.863976,
        "lng": -4.328132
      },
      {
        "lat": 55.863957,
        "lng": -4.328043
      },
      {
        "lat": 55.863947,
        "lng": -4.327996
      },
      {
        "lat": 55.863968,
        "lng": -4.327713
      },
      {
        "lat": 55.863994,
        "lng": -4.327461
      },
      {
        "lat": 55.864051,
        "lng": -4.327253
      },
      {
        "lat": 55.86408,
        "lng": -4.327134
      },
      {
        "lat": 55.864097,
        "lng": -4.326837
      },
      {
        "lat": 55.864077,
        "lng": -4.325708
      },
      {
        "lat": 55.864076,
        "lng": -4.32565
      },
      {
        "lat": 55.864011,
        "lng": -4.321949
      },
      {
        "lat": 55.863995,
        "lng": -4.321063
      },
      {
        "lat": 55.863959,
        "lng": -4.319
      },
      {
        "lat": 55.863953,
        "lng": -4.318461
      },
      {
        "lat": 55.863945,
        "lng": -4.317795
      },
      {
        "lat": 55.863943,
        "lng": -4.317576
      },
      {
        "lat": 55.863817,
        "lng": -4.317532
      },
      {
        "lat": 55.863444,
        "lng": -4.317401
      },
      {
        "lat": 55.863369,
        "lng": -4.31737
      },
      {
        "lat": 55.863284,
        "lng": -4.317336
      },
      {
        "lat": 55.863129,
        "lng": -4.317296
      },
      {
        "lat": 55.862993,
        "lng": -4.317285
      },
      {
        "lat": 55.86275,
        "lng": -4.317274
      },
      {
        "lat": 55.862639,
        "lng": -4.317268
      },
      {
        "lat": 55.862519,
        "lng": -4.317258
      },
      {
        "lat": 55.862434,
        "lng": -4.317232
      },
      {
        "lat": 55.862389,
        "lng": -4.31719
      },
      {
        "lat": 55.862294,
        "lng": -4.317062
      },
      {
        "lat": 55.86223,
        "lng": -4.316906
      },
      {
        "lat": 55.862202,
        "lng": -4.316807
      },
      {
        "lat": 55.862182,
        "lng": -4.316688
      },
      {
        "lat": 55.862165,
        "lng": -4.316478
      },
      {
        "lat": 55.862169,
        "lng": -4.316377
      },
      {
        "lat": 55.86221,
        "lng": -4.31598
      },
      {
        "lat": 55.862301,
        "lng": -4.315671
      },
      {
        "lat": 55.862317,
        "lng": -4.315422
      },
      {
        "lat": 55.862317,
        "lng": -4.315325
      },
      {
        "lat": 55.862318,
        "lng": -4.315177
      },
      {
        "lat": 55.862299,
        "lng": -4.314918
      },
      {
        "lat": 55.862244,
        "lng": -4.314303
      },
      {
        "lat": 55.862223,
        "lng": -4.313998
      },
      {
        "lat": 55.862175,
        "lng": -4.313317
      },
      {
        "lat": 55.86217,
        "lng": -4.313254
      },
      {
        "lat": 55.862157,
        "lng": -4.313073
      },
      {
        "lat": 55.862104,
        "lng": -4.312219
      },
      {
        "lat": 55.862089,
        "lng": -4.311981
      },
      {
        "lat": 55.862079,
        "lng": -4.31182
      },
      {
        "lat": 55.862062,
        "lng": -4.311307
      },
      {
        "lat": 55.862049,
        "lng": -4.310861
      },
      {
        "lat": 55.862049,
        "lng": -4.310575
      },
      {
        "lat": 55.862068,
        "lng": -4.310201
      },
      {
        "lat": 55.862077,
        "lng": -4.310067
      },
      {
        "lat": 55.8621,
        "lng": -4.309884
      },
      {
        "lat": 55.862113,
        "lng": -4.309774
      },
      {
        "lat": 55.862083,
        "lng": -4.309408
      },
      {
        "lat": 55.861999,
        "lng": -4.309127
      },
      {
        "lat": 55.861871,
        "lng": -4.308695
      },
      {
        "lat": 55.861783,
        "lng": -4.308399
      },
      {
        "lat": 55.86166,
        "lng": -4.30798
      },
      {
        "lat": 55.861655,
        "lng": -4.307964
      },
      {
        "lat": 55.861351,
        "lng": -4.306928
      },
      {
        "lat": 55.861338,
        "lng": -4.306886
      },
      {
        "lat": 55.861216,
        "lng": -4.306495
      },
      {
        "lat": 55.861113,
        "lng": -4.306166
      },
      {
        "lat": 55.860774,
        "lng": -4.305017
      },
      {
        "lat": 55.860495,
        "lng": -4.30407
      },
      {
        "lat": 55.860216,
        "lng": -4.303138
      },
      {
        "lat": 55.860186,
        "lng": -4.303037
      },
      {
        "lat": 55.860081,
        "lng": -4.302665
      },
      {
        "lat": 55.859716,
        "lng": -4.301443
      },
      {
        "lat": 55.859707,
        "lng": -4.301413
      },
      {
        "lat": 55.859495,
        "lng": -4.30069
      },
      {
        "lat": 55.859457,
        "lng": -4.300562
      },
      {
        "lat": 55.859321,
        "lng": -4.300117
      },
      {
        "lat": 55.859242,
        "lng": -4.299857
      },
      {
        "lat": 55.859192,
        "lng": -4.299707
      },
      {
        "lat": 55.859185,
        "lng": -4.299686
      },
      {
        "lat": 55.859126,
        "lng": -4.299534
      },
      {
        "lat": 55.859104,
        "lng": -4.299481
      },
      {
        "lat": 55.859073,
        "lng": -4.299407
      },
      {
        "lat": 55.858984,
        "lng": -4.299236
      },
      {
        "lat": 55.85888,
        "lng": -4.299086
      },
      {
        "lat": 55.858788,
        "lng": -4.298977
      },
      {
        "lat": 55.858678,
        "lng": -4.29889
      },
      {
        "lat": 55.858577,
        "lng": -4.298838
      },
      {
        "lat": 55.858485,
        "lng": -4.29881
      },
      {
        "lat": 55.858373,
        "lng": -4.298792
      },
      {
        "lat": 55.85832,
        "lng": -4.298789
      },
      {
        "lat": 55.858206,
        "lng": -4.29881
      },
      {
        "lat": 55.858073,
        "lng": -4.298843
      },
      {
        "lat": 55.857947,
        "lng": -4.298904
      },
      {
        "lat": 55.857778,
        "lng": -4.298977
      },
      {
        "lat": 55.857527,
        "lng": -4.299104
      },
      {
        "lat": 55.857424,
        "lng": -4.299156
      },
      {
        "lat": 55.857273,
        "lng": -4.299236
      },
      {
        "lat": 55.857134,
        "lng": -4.299309
      },
      {
        "lat": 55.856739,
        "lng": -4.299467
      },
      {
        "lat": 55.85672,
        "lng": -4.299476
      },
      {
        "lat": 55.856488,
        "lng": -4.299592
      },
      {
        "lat": 55.856354,
        "lng": -4.29965
      },
      {
        "lat": 55.85629,
        "lng": -4.299675
      },
      {
        "lat": 55.856248,
        "lng": -4.29969
      },
      {
        "lat": 55.856128,
        "lng": -4.299681
      },
      {
        "lat": 55.855994,
        "lng": -4.299669
      },
      {
        "lat": 55.855862,
        "lng": -4.299657
      },
      {
        "lat": 55.855783,
        "lng": -4.299586
      },
      {
        "lat": 55.85571,
        "lng": -4.299462
      },
      {
        "lat": 55.855617,
        "lng": -4.299218
      },
      {
        "lat": 55.855531,
        "lng": -4.298874
      },
      {
        "lat": 55.855414,
        "lng": -4.29833
      },
      {
        "lat": 55.85534,
        "lng": -4.297956
      },
      {
        "lat": 55.855297,
        "lng": -4.29772
      },
      {
        "lat": 55.855262,
        "lng": -4.297489
      },
      {
        "lat": 55.855244,
        "lng": -4.297312
      },
      {
        "lat": 55.855224,
        "lng": -4.297024
      },
      {
        "lat": 55.855213,
        "lng": -4.296714
      },
      {
        "lat": 55.855212,
        "lng": -4.296518
      },
      {
        "lat": 55.855223,
        "lng": -4.296248
      },
      {
        "lat": 55.855252,
        "lng": -4.295916
      },
      {
        "lat": 55.855265,
        "lng": -4.29581
      },
      {
        "lat": 55.855285,
        "lng": -4.295659
      },
      {
        "lat": 55.855347,
        "lng": -4.295279
      },
      {
        "lat": 55.855388,
        "lng": -4.29509
      },
      {
        "lat": 55.85544,
        "lng": -4.294887
      },
      {
        "lat": 55.855522,
        "lng": -4.294631
      },
      {
        "lat": 55.855626,
        "lng": -4.294334
      },
      {
        "lat": 55.85569,
        "lng": -4.294164
      },
      {
        "lat": 55.855867,
        "lng": -4.293766
      },
      {
        "lat": 55.856101,
        "lng": -4.293255
      },
      {
        "lat": 55.856156,
        "lng": -4.293111
      },
      {
        "lat": 55.856281,
        "lng": -4.292785
      },
      {
        "lat": 55.856343,
        "lng": -4.292603
      },
      {
        "lat": 55.856411,
        "lng": -4.292394
      },
      {
        "lat": 55.856423,
        "lng": -4.292356
      },
      {
        "lat": 55.856487,
        "lng": -4.292124
      },
      {
        "lat": 55.856614,
        "lng": -4.29166
      },
      {
        "lat": 55.85669,
        "lng": -4.291343
      },
      {
        "lat": 55.856732,
        "lng": -4.291081
      },
      {
        "lat": 55.856741,
        "lng": -4.291003
      },
      {
        "lat": 55.856776,
        "lng": -4.290674
      },
      {
        "lat": 55.856781,
        "lng": -4.290596
      },
      {
        "lat": 55.856782,
        "lng": -4.290567
      },
      {
        "lat": 55.856789,
        "lng": -4.290378
      },
      {
        "lat": 55.856794,
        "lng": -4.290214
      },
      {
        "lat": 55.856792,
        "lng": -4.289737
      },
      {
        "lat": 55.856752,
        "lng": -4.289299
      },
      {
        "lat": 55.856697,
        "lng": -4.288851
      },
      {
        "lat": 55.856508,
        "lng": -4.287319
      },
      {
        "lat": 55.856418,
        "lng": -4.286743
      },
      {
        "lat": 55.856343,
        "lng": -4.286382
      },
      {
        "lat": 55.856254,
        "lng": -4.285951
      },
      {
        "lat": 55.856212,
        "lng": -4.285766
      },
      {
        "lat": 55.856118,
        "lng": -4.285323
      },
      {
        "lat": 55.856078,
        "lng": -4.285138
      },
      {
        "lat": 55.856157,
        "lng": -4.284947
      },
      {
        "lat": 55.856264,
        "lng": -4.284661
      },
      {
        "lat": 55.85632,
        "lng": -4.284535
      },
      {
        "lat": 55.856518,
        "lng": -4.284139
      },
      {
        "lat": 55.856576,
        "lng": -4.284016
      },
      {
        "lat": 55.856892,
        "lng": -4.283292
      },
      {
        "lat": 55.857306,
        "lng": -4.282346
      },
      {
        "lat": 55.857441,
        "lng": -4.282037
      },
      {
        "lat": 55.857545,
        "lng": -4.281854
      },
      {
        "lat": 55.857621,
        "lng": -4.281761
      },
      {
        "lat": 55.857647,
        "lng": -4.28173
      },
      {
        "lat": 55.857723,
        "lng": -4.281644
      },
      {
        "lat": 55.857806,
        "lng": -4.28163
      },
      {
        "lat": 55.857798,
        "lng": -4.281587
      },
      {
        "lat": 55.857773,
        "lng": -4.281444
      },
      {
        "lat": 55.857764,
        "lng": -4.281394
      },
      {
        "lat": 55.857732,
        "lng": -4.281193
      },
      {
        "lat": 55.857581,
        "lng": -4.280278
      },
      {
        "lat": 55.857547,
        "lng": -4.280069
      },
      {
        "lat": 55.857416,
        "lng": -4.279217
      },
      {
        "lat": 55.857392,
        "lng": -4.279031
      },
      {
        "lat": 55.857373,
        "lng": -4.278849
      },
      {
        "lat": 55.857367,
        "lng": -4.278753
      },
      {
        "lat": 55.857364,
        "lng": -4.278661
      },
      {
        "lat": 55.857361,
        "lng": -4.278592
      },
      {
        "lat": 55.857347,
        "lng": -4.278261
      },
      {
        "lat": 55.857191,
        "lng": -4.276729
      },
      {
        "lat": 55.857116,
        "lng": -4.275943
      },
      {
        "lat": 55.857088,
        "lng": -4.275675
      },
      {
        "lat": 55.85707,
        "lng": -4.275521
      },
      {
        "lat": 55.857055,
        "lng": -4.2754
      },
      {
        "lat": 55.85704,
        "lng": -4.275302
      },
      {
        "lat": 55.85703,
        "lng": -4.275234
      },
      {
        "lat": 55.857022,
        "lng": -4.275178
      },
      {
        "lat": 55.857014,
        "lng": -4.275127
      },
      {
        "lat": 55.856944,
        "lng": -4.274665
      },
      {
        "lat": 55.85686,
        "lng": -4.274121
      },
      {
        "lat": 55.856851,
        "lng": -4.274057
      },
      {
        "lat": 55.856835,
        "lng": -4.273949
      },
      {
        "lat": 55.856809,
        "lng": -4.273664
      },
      {
        "lat": 55.856802,
        "lng": -4.273562
      },
      {
        "lat": 55.856802,
        "lng": -4.273547
      },
      {
        "lat": 55.856796,
        "lng": -4.273424
      },
      {
        "lat": 55.856788,
        "lng": -4.273262
      },
      {
        "lat": 55.856782,
        "lng": -4.273159
      },
      {
        "lat": 55.856771,
        "lng": -4.272961
      },
      {
        "lat": 55.856748,
        "lng": -4.272574
      },
      {
        "lat": 55.856728,
        "lng": -4.272221
      },
      {
        "lat": 55.856722,
        "lng": -4.272067
      },
      {
        "lat": 55.85672,
        "lng": -4.271929
      },
      {
        "lat": 55.856721,
        "lng": -4.27178
      },
      {
        "lat": 55.85673,
        "lng": -4.271359
      },
      {
        "lat": 55.856732,
        "lng": -4.271265
      },
      {
        "lat": 55.856732,
        "lng": -4.271247
      },
      {
        "lat": 55.856763,
        "lng": -4.271043
      },
      {
        "lat": 55.856773,
        "lng": -4.270617
      },
      {
        "lat": 55.856774,
        "lng": -4.270557
      },
      {
        "lat": 55.856775,
        "lng": -4.27052
      },
      {
        "lat": 55.856777,
        "lng": -4.270431
      },
      {
        "lat": 55.856784,
        "lng": -4.27
      },
      {
        "lat": 55.856785,
        "lng": -4.26991
      },
      {
        "lat": 55.856787,
        "lng": -4.269801
      },
      {
        "lat": 55.856789,
        "lng": -4.26966
      },
      {
        "lat": 55.856786,
        "lng": -4.269482
      },
      {
        "lat": 55.856751,
        "lng": -4.269118
      },
      {
        "lat": 55.856746,
        "lng": -4.268852
      },
      {
        "lat": 55.856742,
        "lng": -4.26862
      },
      {
        "lat": 55.856736,
        "lng": -4.268288
      },
      {
        "lat": 55.85673,
        "lng": -4.26797
      },
      {
        "lat": 55.856728,
        "lng": -4.267798
      },
      {
        "lat": 55.856729,
        "lng": -4.267629
      },
      {
        "lat": 55.856734,
        "lng": -4.267421
      },
      {
        "lat": 55.856739,
        "lng": -4.267248
      },
      {
        "lat": 55.856809,
        "lng": -4.26621
      },
      {
        "lat": 55.856868,
        "lng": -4.265336
      },
      {
        "lat": 55.856872,
        "lng": -4.265276
      },
      {
        "lat": 55.856876,
        "lng": -4.265216
      },
      {
        "lat": 55.856881,
        "lng": -4.265146
      },
      {
        "lat": 55.856894,
        "lng": -4.264937
      },
      {
        "lat": 55.856903,
        "lng": -4.264793
      },
      {
        "lat": 55.856909,
        "lng": -4.264682
      },
      {
        "lat": 55.856915,
        "lng": -4.264523
      },
      {
        "lat": 55.856916,
        "lng": -4.264489
      },
      {
        "lat": 55.856925,
        "lng": -4.264332
      },
      {
        "lat": 55.856938,
        "lng": -4.264105
      },
      {
        "lat": 55.856943,
        "lng": -4.263909
      },
      {
        "lat": 55.856941,
        "lng": -4.263708
      },
      {
        "lat": 55.856941,
        "lng": -4.263589
      },
      {
        "lat": 55.856935,
        "lng": -4.263471
      },
      {
        "lat": 55.856918,
        "lng": -4.263304
      },
      {
        "lat": 55.856891,
        "lng": -4.263076
      },
      {
        "lat": 55.856884,
        "lng": -4.263019
      },
      {
        "lat": 55.856864,
        "lng": -4.262827
      },
      {
        "lat": 55.85684,
        "lng": -4.262616
      },
      {
        "lat": 55.856775,
        "lng": -4.262126
      },
      {
        "lat": 55.856709,
        "lng": -4.261535
      },
      {
        "lat": 55.856686,
        "lng": -4.261251
      },
      {
        "lat": 55.856677,
        "lng": -4.261157
      },
      {
        "lat": 55.856671,
        "lng": -4.261052
      },
      {
        "lat": 55.856663,
        "lng": -4.260914
      },
      {
        "lat": 55.856656,
        "lng": -4.260713
      },
      {
        "lat": 55.856631,
        "lng": -4.259988
      },
      {
        "lat": 55.856629,
        "lng": -4.259931
      },
      {
        "lat": 55.856623,
        "lng": -4.259731
      },
      {
        "lat": 55.856604,
        "lng": -4.259272
      },
      {
        "lat": 55.856584,
        "lng": -4.258911
      },
      {
        "lat": 55.856545,
        "lng": -4.258522
      },
      {
        "lat": 55.856504,
        "lng": -4.25821
      },
      {
        "lat": 55.85645,
        "lng": -4.257823
      },
      {
        "lat": 55.856443,
        "lng": -4.257767
      },
      {
        "lat": 55.856415,
        "lng": -4.257564
      },
      {
        "lat": 55.856325,
        "lng": -4.257586
      },
      {
        "lat": 55.856197,
        "lng": -4.257628
      },
      {
        "lat": 55.85481,
        "lng": -4.25812
      },
      {
        "lat": 55.854761,
        "lng": -4.258137
      },
      {
        "lat": 55.8547,
        "lng": -4.258158
      },
      {
        "lat": 55.854134,
        "lng": -4.258371
      },
      {
        "lat": 55.853821,
        "lng": -4.258492
      },
      {
        "lat": 55.853716,
        "lng": -4.258532
      },
      {
        "lat": 55.853622,
        "lng": -4.25857
      },
      {
        "lat": 55.852715,
        "lng": -4.258932
      },
      {
        "lat": 55.852895,
        "lng": -4.260439
      },
      {
        "lat": 55.853782,
        "lng": -4.260107
      },
      {
        "lat": 55.853887,
        "lng": -4.260067
      },
      {
        "lat": 55.854711,
        "lng": -4.259769
      },
      {
        "lat": 55.854743,
        "lng": -4.259766
      },
      {
        "lat": 55.854842,
        "lng": -4.259759
      },
      {
        "lat": 55.854849,
        "lng": -4.259759
      },
      {
        "lat": 55.854875,
        "lng": -4.259757
      },
      {
        "lat": 55.854945,
        "lng": -4.259755
      },
      {
        "lat": 55.855107,
        "lng": -4.259753
      },
      {
        "lat": 55.856328,
        "lng": -4.259734
      },
      {
        "lat": 55.856347,
        "lng": -4.259735
      },
      {
        "lat": 55.856385,
        "lng": -4.259735
      },
      {
        "lat": 55.856434,
        "lng": -4.259736
      },
      {
        "lat": 55.856522,
        "lng": -4.259732
      },
      {
        "lat": 55.856609,
        "lng": -4.259731
      },
      {
        "lat": 55.856623,
        "lng": -4.259731
      },
      {
        "lat": 55.856604,
        "lng": -4.259272
      },
      {
        "lat": 55.856584,
        "lng": -4.258911
      },
      {
        "lat": 55.856545,
        "lng": -4.258522
      },
      {
        "lat": 55.856504,
        "lng": -4.25821
      },
      {
        "lat": 55.85645,
        "lng": -4.257823
      },
      {
        "lat": 55.856443,
        "lng": -4.257767
      },
      {
        "lat": 55.856415,
        "lng": -4.257564
      },
      {
        "lat": 55.856325,
        "lng": -4.257586
      },
      {
        "lat": 55.85635,
        "lng": -4.257883
      },
      {
        "lat": 55.856393,
        "lng": -4.258201
      },
      {
        "lat": 55.856404,
        "lng": -4.258297
      },
      {
        "lat": 55.856436,
        "lng": -4.258581
      },
      {
        "lat": 55.856464,
        "lng": -4.258965
      },
      {
        "lat": 55.856479,
        "lng": -4.259207
      },
      {
        "lat": 55.856498,
        "lng": -4.259459
      },
      {
        "lat": 55.856503,
        "lng": -4.259519
      },
      {
        "lat": 55.856522,
        "lng": -4.259732
      },
      {
        "lat": 55.856537,
        "lng": -4.259896
      },
      {
        "lat": 55.856546,
        "lng": -4.260026
      },
      {
        "lat": 55.856553,
        "lng": -4.260189
      },
      {
        "lat": 55.856577,
        "lng": -4.260802
      },
      {
        "lat": 55.856594,
        "lng": -4.261136
      },
      {
        "lat": 55.856601,
        "lng": -4.261303
      },
      {
        "lat": 55.856626,
        "lng": -4.261609
      },
      {
        "lat": 55.856684,
        "lng": -4.26218
      },
      {
        "lat": 55.856706,
        "lng": -4.262402
      },
      {
        "lat": 55.85674,
        "lng": -4.262661
      },
      {
        "lat": 55.856752,
        "lng": -4.262779
      },
      {
        "lat": 55.85678,
        "lng": -4.2628
      },
      {
        "lat": 55.8568,
        "lng": -4.262812
      },
      {
        "lat": 55.856818,
        "lng": -4.262819
      },
      {
        "lat": 55.856864,
        "lng": -4.262827
      },
      {
        "lat": 55.857402,
        "lng": -4.26276
      },
      {
        "lat": 55.857616,
        "lng": -4.262736
      },
      {
        "lat": 55.857772,
        "lng": -4.262717
      },
      {
        "lat": 55.857853,
        "lng": -4.262707
      },
      {
        "lat": 55.858159,
        "lng": -4.262669
      },
      {
        "lat": 55.858166,
        "lng": -4.262668
      },
      {
        "lat": 55.858737,
        "lng": -4.262593
      },
      {
        "lat": 55.858874,
        "lng": -4.262563
      },
      {
        "lat": 55.859354,
        "lng": -4.262393
      },
      {
        "lat": 55.859841,
        "lng": -4.262222
      },
      {
        "lat": 55.860172,
        "lng": -4.262094
      },
      {
        "lat": 55.860049,
        "lng": -4.2606
      },
      {
        "lat": 55.859731,
        "lng": -4.260715
      },
      {
        "lat": 55.859661,
        "lng": -4.259808
      },
      {
        "lat": 55.859731,
        "lng": -4.260715
      },
      {
        "lat": 55.859841,
        "lng": -4.262222
      },
      {
        "lat": 55.860172,
        "lng": -4.262094
      },
      {
        "lat": 55.860499,
        "lng": -4.261967
      },
      {
        "lat": 55.860521,
        "lng": -4.261958
      },
      {
        "lat": 55.86058,
        "lng": -4.261937
      },
      {
        "lat": 55.860899,
        "lng": -4.261823
      },
      {
        "lat": 55.861227,
        "lng": -4.261703
      },
      {
        "lat": 55.861301,
        "lng": -4.261676
      },
      {
        "lat": 55.861412,
        "lng": -4.261635
      },
      {
        "lat": 55.86167,
        "lng": -4.261541
      },
      {
        "lat": 55.862037,
        "lng": -4.26141
      },
      {
        "lat": 55.862458,
        "lng": -4.261255
      },
      {
        "lat": 55.862882,
        "lng": -4.261091
      },
      {
        "lat": 55.862704,
        "lng": -4.259608
      },
      {
        "lat": 55.862579,
        "lng": -4.258605
      },
      {
        "lat": 55.862505,
        "lng": -4.258011
      },
      {
        "lat": 55.862401,
        "lng": -4.257097
      },
      {
        "lat": 55.86232,
        "lng": -4.256388
      },
      {
        "lat": 55.862222,
        "lng": -4.25556
      },
      {
        "lat": 55.86217,
        "lng": -4.255119
      },
      {
        "lat": 55.862147,
        "lng": -4.254958
      },
      {
        "lat": 55.862077,
        "lng": -4.254404
      },
      {
        "lat": 55.862012,
        "lng": -4.254394
      },
      {
        "lat": 55.861971,
        "lng": -4.254371
      },
      {
        "lat": 55.861932,
        "lng": -4.254343
      },
      {
        "lat": 55.86191,
        "lng": -4.254317
      },
      {
        "lat": 55.8619,
        "lng": -4.254282
      },
      {
        "lat": 55.861895,
        "lng": -4.254231
      },
      {
        "lat": 55.861841,
        "lng": -4.253804
      },
      {
        "lat": 55.861839,
        "lng": -4.253741
      },
      {
        "lat": 55.861846,
        "lng": -4.253698
      },
      {
        "lat": 55.861862,
        "lng": -4.25366
      },
      {
        "lat": 55.861888,
        "lng": -4.253626
      },
      {
        "lat": 55.861952,
        "lng": -4.25352
      },
      {
        "lat": 55.861963,
        "lng": -4.253494
      },
      {
        "lat": 55.861968,
        "lng": -4.253464
      },
      {
        "lat": 55.861973,
        "lng": -4.253387
      },
      {
        "lat": 55.861881,
        "lng": -4.252652
      },
      {
        "lat": 55.861856,
        "lng": -4.25245
      },
      {
        "lat": 55.86183,
        "lng": -4.252223
      },
      {
        "lat": 55.861799,
        "lng": -4.25195
      },
      {
        "lat": 55.861716,
        "lng": -4.25126
      },
      {
        "lat": 55.861562,
        "lng": -4.250026
      },
      {
        "lat": 55.861429,
        "lng": -4.248872
      },
      {
        "lat": 55.861823,
        "lng": -4.24873
      },
      {
        "lat": 55.862087,
        "lng": -4.248635
      },
      {
        "lat": 55.86232,
        "lng": -4.248551
      },
      {
        "lat": 55.863054,
        "lng": -4.248281
      },
      {
        "lat": 55.862991,
        "lng": -4.247639
      },
      {
        "lat": 55.862981,
        "lng": -4.247523
      },
      {
        "lat": 55.862962,
        "lng": -4.247223
      },
      {
        "lat": 55.862937,
        "lng": -4.246815
      },
      {
        "lat": 55.862936,
        "lng": -4.246782
      },
      {
        "lat": 55.862934,
        "lng": -4.246583
      },
      {
        "lat": 55.862941,
        "lng": -4.246309
      },
      {
        "lat": 55.86295,
        "lng": -4.245969
      },
      {
        "lat": 55.862971,
        "lng": -4.245154
      },
      {
        "lat": 55.862974,
        "lng": -4.245087
      },
      {
        "lat": 55.862974,
        "lng": -4.24504
      },
      {
        "lat": 55.86303,
        "lng": -4.243104
      },
      {
        "lat": 55.863029,
        "lng": -4.242961
      },
      {
        "lat": 55.863042,
        "lng": -4.24258
      },
      {
        "lat": 55.863054,
        "lng": -4.242153
      },
      {
        "lat": 55.863072,
        "lng": -4.240972
      },
      {
        "lat": 55.863079,
        "lng": -4.240645
      },
      {
        "lat": 55.863078,
        "lng": -4.240506
      },
      {
        "lat": 55.863083,
        "lng": -4.240122
      },
      {
        "lat": 55.863331,
        "lng": -4.239587
      },
      {
        "lat": 55.863597,
        "lng": -4.239152
      },
      {
        "lat": 55.863709,
        "lng": -4.239002
      },
      {
        "lat": 55.863799,
        "lng": -4.238851
      },
      {
        "lat": 55.863839,
        "lng": -4.238764
      },
      {
        "lat": 55.863965,
        "lng": -4.238464
      },
      {
        "lat": 55.864057,
        "lng": -4.238246
      },
      {
        "lat": 55.864208,
        "lng": -4.237888
      },
      {
        "lat": 55.86429,
        "lng": -4.237669
      },
      {
        "lat": 55.864313,
        "lng": -4.237607
      },
      {
        "lat": 55.864326,
        "lng": -4.237572
      },
      {
        "lat": 55.864355,
        "lng": -4.23751
      },
      {
        "lat": 55.864389,
        "lng": -4.237445
      },
      {
        "lat": 55.864519,
        "lng": -4.237362
      },
      {
        "lat": 55.8648,
        "lng": -4.23718
      },
      {
        "lat": 55.86506,
        "lng": -4.236919
      },
      {
        "lat": 55.865214,
        "lng": -4.236759
      },
      {
        "lat": 55.865329,
        "lng": -4.236684
      },
      {
        "lat": 55.865522,
        "lng": -4.236575
      },
      {
        "lat": 55.865801,
        "lng": -4.236407
      },
      {
        "lat": 55.866021,
        "lng": -4.23623
      },
      {
        "lat": 55.866146,
        "lng": -4.236107
      },
      {
        "lat": 55.866259,
        "lng": -4.235967
      },
      {
        "lat": 55.866312,
        "lng": -4.235895
      },
      {
        "lat": 55.866366,
        "lng": -4.235811
      },
      {
        "lat": 55.866421,
        "lng": -4.235712
      },
      {
        "lat": 55.866475,
        "lng": -4.235606
      },
      {
        "lat": 55.866528,
        "lng": -4.235498
      },
      {
        "lat": 55.866574,
        "lng": -4.235385
      },
      {
        "lat": 55.866618,
        "lng": -4.235267
      },
      {
        "lat": 55.866654,
        "lng": -4.235151
      },
      {
        "lat": 55.866694,
        "lng": -4.235019
      },
      {
        "lat": 55.866723,
        "lng": -4.234898
      },
      {
        "lat": 55.866751,
        "lng": -4.234773
      },
      {
        "lat": 55.866776,
        "lng": -4.234646
      },
      {
        "lat": 55.8668,
        "lng": -4.234503
      },
      {
        "lat": 55.86682,
        "lng": -4.234356
      },
      {
        "lat": 55.866835,
        "lng": -4.234211
      },
      {
        "lat": 55.866847,
        "lng": -4.234027
      },
      {
        "lat": 55.866853,
        "lng": -4.233853
      },
      {
        "lat": 55.866853,
        "lng": -4.233691
      },
      {
        "lat": 55.866848,
        "lng": -4.233501
      },
      {
        "lat": 55.866836,
        "lng": -4.233301
      },
      {
        "lat": 55.866821,
        "lng": -4.233139
      },
      {
        "lat": 55.8668,
        "lng": -4.232973
      },
      {
        "lat": 55.866768,
        "lng": -4.23275
      },
      {
        "lat": 55.866715,
        "lng": -4.232414
      },
      {
        "lat": 55.86658,
        "lng": -4.231627
      },
      {
        "lat": 55.866551,
        "lng": -4.231454
      },
      {
        "lat": 55.866521,
        "lng": -4.23127
      },
      {
        "lat": 55.866491,
        "lng": -4.231081
      },
      {
        "lat": 55.866464,
        "lng": -4.230886
      },
      {
        "lat": 55.866434,
        "lng": -4.230666
      },
      {
        "lat": 55.866375,
        "lng": -4.230259
      },
      {
        "lat": 55.866336,
        "lng": -4.2297
      },
      {
        "lat": 55.86629,
        "lng": -4.22902
      },
      {
        "lat": 55.866194,
        "lng": -4.228006
      },
      {
        "lat": 55.866164,
        "lng": -4.226886
      },
      {
        "lat": 55.866152,
        "lng": -4.226144
      },
      {
        "lat": 55.866151,
        "lng": -4.225246
      },
      {
        "lat": 55.866157,
        "lng": -4.224301
      },
      {
        "lat": 55.86617,
        "lng": -4.223789
      },
      {
        "lat": 55.866193,
        "lng": -4.223236
      },
      {
        "lat": 55.866225,
        "lng": -4.22276
      },
      {
        "lat": 55.866258,
        "lng": -4.222405
      },
      {
        "lat": 55.866304,
        "lng": -4.221933
      },
      {
        "lat": 55.86636,
        "lng": -4.221509
      },
      {
        "lat": 55.866426,
        "lng": -4.221025
      },
      {
        "lat": 55.866574,
        "lng": -4.22013
      },
      {
        "lat": 55.866642,
        "lng": -4.219699
      },
      {
        "lat": 55.86673,
        "lng": -4.219113
      },
      {
        "lat": 55.866782,
        "lng": -4.218728
      },
      {
        "lat": 55.86684,
        "lng": -4.218282
      },
      {
        "lat": 55.866882,
        "lng": -4.217878
      },
      {
        "lat": 55.866941,
        "lng": -4.217056
      },
      {
        "lat": 55.866988,
        "lng": -4.216066
      },
      {
        "lat": 55.867055,
        "lng": -4.214924
      },
      {
        "lat": 55.867088,
        "lng": -4.214399
      },
      {
        "lat": 55.867113,
        "lng": -4.214067
      },
      {
        "lat": 55.867149,
        "lng": -4.213647
      },
      {
        "lat": 55.867189,
        "lng": -4.213308
      },
      {
        "lat": 55.867224,
        "lng": -4.213028
      },
      {
        "lat": 55.8673,
        "lng": -4.212566
      },
      {
        "lat": 55.867388,
        "lng": -4.212103
      },
      {
        "lat": 55.868234,
        "lng": -4.208322
      },
      {
        "lat": 55.86867,
        "lng": -4.206273
      },
      {
        "lat": 55.868816,
        "lng": -4.205699
      },
      {
        "lat": 55.868953,
        "lng": -4.205188
      },
      {
        "lat": 55.869095,
        "lng": -4.204685
      },
      {
        "lat": 55.869365,
        "lng": -4.203753
      },
      {
        "lat": 55.869598,
        "lng": -4.20299
      },
      {
        "lat": 55.869817,
        "lng": -4.20234
      },
      {
        "lat": 55.869971,
        "lng": -4.201886
      },
      {
        "lat": 55.870111,
        "lng": -4.201495
      },
      {
        "lat": 55.870715,
        "lng": -4.199836
      },
      {
        "lat": 55.870876,
        "lng": -4.199363
      },
      {
        "lat": 55.871134,
        "lng": -4.198575
      },
      {
        "lat": 55.871409,
        "lng": -4.197709
      },
      {
        "lat": 55.871585,
        "lng": -4.197108
      },
      {
        "lat": 55.871752,
        "lng": -4.19652
      },
      {
        "lat": 55.87185,
        "lng": -4.19613
      },
      {
        "lat": 55.872045,
        "lng": -4.195284
      },
      {
        "lat": 55.872192,
        "lng": -4.194624
      },
      {
        "lat": 55.872302,
        "lng": -4.194115
      },
      {
        "lat": 55.872412,
        "lng": -4.193663
      },
      {
        "lat": 55.872515,
        "lng": -4.193279
      },
      {
        "lat": 55.872655,
        "lng": -4.1928
      },
      {
        "lat": 55.872825,
        "lng": -4.192277
      },
      {
        "lat": 55.872925,
        "lng": -4.191981
      },
      {
        "lat": 55.873385,
        "lng": -4.190716
      },
      {
        "lat": 55.873585,
        "lng": -4.190083
      },
      {
        "lat": 55.873795,
        "lng": -4.189329
      },
      {
        "lat": 55.874009,
        "lng": -4.188074
      },
      {
        "lat": 55.874072,
        "lng": -4.187353
      },
      {
        "lat": 55.874088,
        "lng": -4.186669
      },
      {
        "lat": 55.874064,
        "lng": -4.185898
      },
      {
        "lat": 55.873993,
        "lng": -4.185174
      },
      {
        "lat": 55.873886,
        "lng": -4.184537
      },
      {
        "lat": 55.873785,
        "lng": -4.184097
      },
      {
        "lat": 55.873597,
        "lng": -4.183478
      },
      {
        "lat": 55.873287,
        "lng": -4.182696
      },
      {
        "lat": 55.873031,
        "lng": -4.182168
      },
      {
        "lat": 55.872468,
        "lng": -4.181125
      },
      {
        "lat": 55.87207,
        "lng": -4.180364
      },
      {
        "lat": 55.871596,
        "lng": -4.179322
      },
      {
        "lat": 55.871029,
        "lng": -4.177914
      },
      {
        "lat": 55.870674,
        "lng": -4.177094
      },
      {
        "lat": 55.870332,
        "lng": -4.176445
      },
      {
        "lat": 55.869975,
        "lng": -4.175864
      },
      {
        "lat": 55.869707,
        "lng": -4.175475
      },
      {
        "lat": 55.869406,
        "lng": -4.17507
      },
      {
        "lat": 55.868827,
        "lng": -4.17419
      },
      {
        "lat": 55.86851,
        "lng": -4.173583
      },
      {
        "lat": 55.868294,
        "lng": -4.173051
      },
      {
        "lat": 55.868102,
        "lng": -4.172411
      },
      {
        "lat": 55.867949,
        "lng": -4.171675
      },
      {
        "lat": 55.867846,
        "lng": -4.170853
      },
      {
        "lat": 55.867795,
        "lng": -4.170177
      },
      {
        "lat": 55.867801,
        "lng": -4.1693
      },
      {
        "lat": 55.867896,
        "lng": -4.168146
      },
      {
        "lat": 55.868365,
        "lng": -4.164174
      },
      {
        "lat": 55.868778,
        "lng": -4.161801
      },
      {
        "lat": 55.868878,
        "lng": -4.161255
      },
      {
        "lat": 55.868953,
        "lng": -4.16097
      },
      {
        "lat": 55.869046,
        "lng": -4.160683
      },
      {
        "lat": 55.869187,
        "lng": -4.160394
      },
      {
        "lat": 55.869322,
        "lng": -4.160175
      },
      {
        "lat": 55.869714,
        "lng": -4.159712
      },
      {
        "lat": 55.869895,
        "lng": -4.159458
      },
      {
        "lat": 55.870028,
        "lng": -4.159131
      },
      {
        "lat": 55.870097,
        "lng": -4.158857
      },
      {
        "lat": 55.870209,
        "lng": -4.158123
      },
      {
        "lat": 55.870276,
        "lng": -4.157991
      },
      {
        "lat": 55.870353,
        "lng": -4.15796
      },
      {
        "lat": 55.870417,
        "lng": -4.157952
      },
      {
        "lat": 55.870792,
        "lng": -4.158418
      },
      {
        "lat": 55.871286,
        "lng": -4.159062
      },
      {
        "lat": 55.871322,
        "lng": -4.158926
      },
      {
        "lat": 55.871395,
        "lng": -4.158654
      },
      {
        "lat": 55.871431,
        "lng": -4.158175
      },
      {
        "lat": 55.871413,
        "lng": -4.157595
      },
      {
        "lat": 55.871392,
        "lng": -4.157454
      },
      {
        "lat": 55.871343,
        "lng": -4.157128
      },
      {
        "lat": 55.871142,
        "lng": -4.156303
      },
      {
        "lat": 55.871107,
        "lng": -4.15605
      },
      {
        "lat": 55.871037,
        "lng": -4.155111
      },
      {
        "lat": 55.871009,
        "lng": -4.15465
      },
      {
        "lat": 55.870997,
        "lng": -4.154452
      },
      {
        "lat": 55.870954,
        "lng": -4.153735
      },
      {
        "lat": 55.870945,
        "lng": -4.153578
      },
      {
        "lat": 55.870831,
        "lng": -4.151602
      },
      {
        "lat": 55.870832,
        "lng": -4.151349
      },
      {
        "lat": 55.870901,
        "lng": -4.150657
      },
      {
        "lat": 55.870929,
        "lng": -4.15042
      },
      {
        "lat": 55.871019,
        "lng": -4.149654
      },
      {
        "lat": 55.871252,
        "lng": -4.147098
      },
      {
        "lat": 55.871272,
        "lng": -4.14679
      },
      {
        "lat": 55.871319,
        "lng": -4.146082
      },
      {
        "lat": 55.871322,
        "lng": -4.145425
      },
      {
        "lat": 55.871327,
        "lng": -4.145205
      },
      {
        "lat": 55.871334,
        "lng": -4.14481
      },
      {
        "lat": 55.871354,
        "lng": -4.14434
      },
      {
        "lat": 55.871361,
        "lng": -4.14418
      },
      {
        "lat": 55.87137,
        "lng": -4.143998
      },
      {
        "lat": 55.871376,
        "lng": -4.143874
      },
      {
        "lat": 55.871402,
        "lng": -4.143607
      },
      {
        "lat": 55.871459,
        "lng": -4.14316
      },
      {
        "lat": 55.871476,
        "lng": -4.143079
      },
      {
        "lat": 55.871512,
        "lng": -4.142905
      },
      {
        "lat": 55.871556,
        "lng": -4.142702
      },
      {
        "lat": 55.87162,
        "lng": -4.142403
      },
      {
        "lat": 55.871771,
        "lng": -4.141861
      },
      {
        "lat": 55.871776,
        "lng": -4.141841
      },
      {
        "lat": 55.872051,
        "lng": -4.141064
      },
      {
        "lat": 55.872229,
        "lng": -4.14065
      },
      {
        "lat": 55.872407,
        "lng": -4.140242
      },
      {
        "lat": 55.872446,
        "lng": -4.140142
      },
      {
        "lat": 55.872597,
        "lng": -4.139756
      },
      {
        "lat": 55.872792,
        "lng": -4.139243
      },
      {
        "lat": 55.872866,
        "lng": -4.13904
      },
      {
        "lat": 55.873301,
        "lng": -4.137861
      },
      {
        "lat": 55.87352,
        "lng": -4.137245
      },
      {
        "lat": 55.874249,
        "lng": -4.135347
      },
      {
        "lat": 55.874434,
        "lng": -4.134867
      },
      {
        "lat": 55.874561,
        "lng": -4.134499
      },
      {
        "lat": 55.874039,
        "lng": -4.133304
      },
      {
        "lat": 55.873689,
        "lng": -4.132526
      },
      {
        "lat": 55.873337,
        "lng": -4.131742
      },
      {
        "lat": 55.87319,
        "lng": -4.13148
      },
      {
        "lat": 55.872988,
        "lng": -4.131889
      },
      {
        "lat": 55.872889,
        "lng": -4.132142
      },
      {
        "lat": 55.87283,
        "lng": -4.132294
      },
      {
        "lat": 55.872786,
        "lng": -4.132437
      },
      {
        "lat": 55.872745,
        "lng": -4.132591
      },
      {
        "lat": 55.872682,
        "lng": -4.132913
      },
      {
        "lat": 55.872678,
        "lng": -4.132932
      },
      {
        "lat": 55.872671,
        "lng": -4.132966
      },
      {
        "lat": 55.872508,
        "lng": -4.133823
      },
      {
        "lat": 55.87248,
        "lng": -4.133802
      },
      {
        "lat": 55.87245,
        "lng": -4.133799
      },
      {
        "lat": 55.872422,
        "lng": -4.133815
      },
      {
        "lat": 55.872398,
        "lng": -4.133848
      },
      {
        "lat": 55.872383,
        "lng": -4.133893
      },
      {
        "lat": 55.872377,
        "lng": -4.133945
      },
      {
        "lat": 55.872381,
        "lng": -4.133998
      },
      {
        "lat": 55.872396,
        "lng": -4.134044
      },
      {
        "lat": 55.872419,
        "lng": -4.134079
      },
      {
        "lat": 55.872447,
        "lng": -4.134097
      },
      {
        "lat": 55.872288,
        "lng": -4.134523
      },
      {
        "lat": 55.872185,
        "lng": -4.134761
      },
      {
        "lat": 55.87206,
        "lng": -4.134975
      },
      {
        "lat": 55.871829,
        "lng": -4.135117
      },
      {
        "lat": 55.871703,
        "lng": -4.135101
      },
      {
        "lat": 55.871626,
        "lng": -4.135056
      },
      {
        "lat": 55.871553,
        "lng": -4.13499
      },
      {
        "lat": 55.871501,
        "lng": -4.134928
      },
      {
        "lat": 55.871457,
        "lng": -4.134923
      },
      {
        "lat": 55.871411,
        "lng": -4.134942
      },
      {
        "lat": 55.871356,
        "lng": -4.134966
      },
      {
        "lat": 55.871323,
        "lng": -4.135019
      },
      {
        "lat": 55.871301,
        "lng": -4.135087
      },
      {
        "lat": 55.871291,
        "lng": -4.135164
      },
      {
        "lat": 55.871292,
        "lng": -4.135189
      },
      {
        "lat": 55.871294,
        "lng": -4.135242
      },
      {
        "lat": 55.871304,
        "lng": -4.135329
      },
      {
        "lat": 55.871338,
        "lng": -4.135405
      },
      {
        "lat": 55.871366,
        "lng": -4.135455
      },
      {
        "lat": 55.871398,
        "lng": -4.135468
      },
      {
        "lat": 55.871468,
        "lng": -4.135586
      },
      {
        "lat": 55.871548,
        "lng": -4.135805
      },
      {
        "lat": 55.871616,
        "lng": -4.136053
      },
      {
        "lat": 55.87165,
        "lng": -4.136202
      },
      {
        "lat": 55.871663,
        "lng": -4.136253
      },
      {
        "lat": 55.871696,
        "lng": -4.136419
      },
      {
        "lat": 55.871716,
        "lng": -4.136546
      },
      {
        "lat": 55.871759,
        "lng": -4.136689
      },
      {
        "lat": 55.871689,
        "lng": -4.136729
      },
      {
        "lat": 55.871583,
        "lng": -4.136765
      },
      {
        "lat": 55.871465,
        "lng": -4.136786
      },
      {
        "lat": 55.871315,
        "lng": -4.136781
      },
      {
        "lat": 55.871295,
        "lng": -4.136775
      },
      {
        "lat": 55.871188,
        "lng": -4.136745
      },
      {
        "lat": 55.871021,
        "lng": -4.136638
      },
      {
        "lat": 55.870931,
        "lng": -4.136554
      },
      {
        "lat": 55.870837,
        "lng": -4.136444
      },
      {
        "lat": 55.870799,
        "lng": -4.136394
      },
      {
        "lat": 55.870769,
        "lng": -4.136343
      },
      {
        "lat": 55.870717,
        "lng": -4.136242
      },
      {
        "lat": 55.870691,
        "lng": -4.136206
      },
      {
        "lat": 55.870663,
        "lng": -4.136198
      },
      {
        "lat": 55.870636,
        "lng": -4.13621
      },
      {
        "lat": 55.870553,
        "lng": -4.13631
      },
      {
        "lat": 55.870631,
        "lng": -4.136472
      },
      {
        "lat": 55.870701,
        "lng": -4.136582
      },
      {
        "lat": 55.870792,
        "lng": -4.136706
      },
      {
        "lat": 55.870869,
        "lng": -4.136794
      },
      {
        "lat": 55.870942,
        "lng": -4.136856
      },
      {
        "lat": 55.87098,
        "lng": -4.136884
      },
      {
        "lat": 55.871021,
        "lng": -4.136638
      },
      {
        "lat": 55.871188,
        "lng": -4.136745
      },
      {
        "lat": 55.871315,
        "lng": -4.136781
      },
      {
        "lat": 55.871465,
        "lng": -4.136786
      },
      {
        "lat": 55.871583,
        "lng": -4.136765
      },
      {
        "lat": 55.871689,
        "lng": -4.136729
      },
      {
        "lat": 55.871759,
        "lng": -4.136689
      },
      {
        "lat": 55.871716,
        "lng": -4.136546
      },
      {
        "lat": 55.871696,
        "lng": -4.136419
      },
      {
        "lat": 55.871663,
        "lng": -4.136253
      },
      {
        "lat": 55.87165,
        "lng": -4.136202
      },
      {
        "lat": 55.871616,
        "lng": -4.136053
      },
      {
        "lat": 55.871548,
        "lng": -4.135805
      },
      {
        "lat": 55.871546,
        "lng": -4.135596
      },
      {
        "lat": 55.871566,
        "lng": -4.135344
      },
      {
        "lat": 55.871571,
        "lng": -4.135323
      },
      {
        "lat": 55.87173,
        "lng": -4.135211
      },
      {
        "lat": 55.871829,
        "lng": -4.135117
      },
      {
        "lat": 55.87206,
        "lng": -4.134975
      },
      {
        "lat": 55.872185,
        "lng": -4.134761
      },
      {
        "lat": 55.872288,
        "lng": -4.134523
      },
      {
        "lat": 55.872447,
        "lng": -4.134097
      },
      {
        "lat": 55.872471,
        "lng": -4.134098
      },
      {
        "lat": 55.872495,
        "lng": -4.134087
      },
      {
        "lat": 55.872516,
        "lng": -4.134063
      },
      {
        "lat": 55.872532,
        "lng": -4.134031
      },
      {
        "lat": 55.872544,
        "lng": -4.133976
      },
      {
        "lat": 55.872544,
        "lng": -4.133918
      },
      {
        "lat": 55.872531,
        "lng": -4.133864
      },
      {
        "lat": 55.872508,
        "lng": -4.133823
      },
      {
        "lat": 55.872658,
        "lng": -4.133035
      },
      {
        "lat": 55.872671,
        "lng": -4.132966
      },
      {
        "lat": 55.872678,
        "lng": -4.132932
      },
      {
        "lat": 55.872682,
        "lng": -4.132913
      },
      {
        "lat": 55.872745,
        "lng": -4.132591
      },
      {
        "lat": 55.872786,
        "lng": -4.132437
      },
      {
        "lat": 55.87283,
        "lng": -4.132294
      },
      {
        "lat": 55.872988,
        "lng": -4.131889
      },
      {
        "lat": 55.87319,
        "lng": -4.13148
      },
      {
        "lat": 55.873014,
        "lng": -4.130992
      },
      {
        "lat": 55.872944,
        "lng": -4.130838
      },
      {
        "lat": 55.872705,
        "lng": -4.130257
      },
      {
        "lat": 55.872463,
        "lng": -4.129758
      },
      {
        "lat": 55.872184,
        "lng": -4.12911
      },
      {
        "lat": 55.872135,
        "lng": -4.128996
      },
      {
        "lat": 55.871882,
        "lng": -4.128492
      },
      {
        "lat": 55.87171,
        "lng": -4.128287
      },
      {
        "lat": 55.871444,
        "lng": -4.127972
      },
      {
        "lat": 55.871226,
        "lng": -4.127795
      },
      {
        "lat": 55.870697,
        "lng": -4.127352
      },
      {
        "lat": 55.870487,
        "lng": -4.127176
      },
      {
        "lat": 55.870432,
        "lng": -4.127129
      },
      {
        "lat": 55.870285,
        "lng": -4.127009
      },
      {
        "lat": 55.870108,
        "lng": -4.126865
      },
      {
        "lat": 55.869751,
        "lng": -4.126514
      },
      {
        "lat": 55.869603,
        "lng": -4.126297
      },
      {
        "lat": 55.869454,
        "lng": -4.126056
      },
      {
        "lat": 55.86931,
        "lng": -4.12573
      },
      {
        "lat": 55.869281,
        "lng": -4.125665
      },
      {
        "lat": 55.869096,
        "lng": -4.12525
      },
      {
        "lat": 55.868968,
        "lng": -4.124951
      },
      {
        "lat": 55.868948,
        "lng": -4.124911
      },
      {
        "lat": 55.868852,
        "lng": -4.124663
      },
      {
        "lat": 55.868656,
        "lng": -4.12419
      },
      {
        "lat": 55.868593,
        "lng": -4.124003
      },
      {
        "lat": 55.868675,
        "lng": -4.123864
      },
      {
        "lat": 55.869051,
        "lng": -4.123251
      },
      {
        "lat": 55.869093,
        "lng": -4.123173
      },
      {
        "lat": 55.869116,
        "lng": -4.123115
      },
      {
        "lat": 55.869128,
        "lng": -4.123087
      }
    ]
  }
}